[
  {
    "bill_numbers": [
      "1"
    ],
    "chamber": "h",
    "collection": "llhb",
    "committees": [
      "Committee of the Whole House"
    ],
    "congress": "007",
    "dates": [
      "18021220"
    ],
    "description": "Read the first and second time, and committed to a Committee of the whole House on Thursday next. A Bill, For the relief of Insolvent Debtors within the District of Columbia.",
    "page": "",
    "session": "002",
    "tiff_filename": "00010000.tif",
    "volume": "021"
  },
  {
    "bill_numbers": [
      "1"
    ],
    "chamber": "h",
    "collection": "llhb",
    "committees": [],
    "congress": "007",
    "dates": [
      "18021220"
    ],
    "description": "",
    "page": "2",
    "session": "002",
    "tiff_filename": "00020002.tif",
    "volume": "021"
  },
  {
    "bill_numbers": [
      "1"
    ],
    "chamber": "h",
    "collection": "llhb",
    "committees": [],
    "congress": "007",
    "dates": [
      "18021220"
    ],
    "description": "",
    "page": "3",
    "session": "002",
    "tiff_filename": "00030003.tif",
    "volume": "021"
  },
  {
    "bill_numbers": [
      "1"
    ],
    "chamber": "h",
    "collection": "llhb",
    "committees": [],
    "congress": "007",
    "dates": [
      "18021220"
    ],
    "description": "",
    "page": "4",
    "session": "002",
    "tiff_filename": "00040004.tif",
    "volume": "021"
  },
  {
    "bill_numbers": [
      "1"
    ],
    "chamber": "h",
    "collection": "llhb",
    "committees": [],
    "congress": "007",
    "dates": [
      "18021220"
    ],
    "description": "",
    "page": "5",
    "session": "002",
    "tiff_filename": "00050005.tif",
    "volume": "021"
  },
  {
    "bill_numbers": [
      "1"
    ],
    "chamber": "h",
    "collection": "llhb",
    "committees": [],
    "congress": "007",
    "dates": [
      "18021220"
    ],
    "description": "",
    "page": "6",
    "session": "002",
    "tiff_filename": "00060006.tif",
    "volume": "021"
  },
  {
    "bill_numbers": [
      "1"
    ],
    "chamber": "h",
    "collection": "llhb",
    "committees": [],
    "congress": "007",
    "dates": [
      "18021220"
    ],
    "description": "",
    "page": "7",
    "session": "002",
    "tiff_filename": "00070007.tif",
    "volume": "021"
  },
  {
    "bill_numbers": [
      "1"
    ],
    "chamber": "h",
    "collection": "llhb",
    "committees": [],
    "congress": "007",
    "dates": [
      "18021220"
    ],
    "description": "",
    "page": "8",
    "session": "002",
    "tiff_filename": "00080008.tif",
    "volume": "021"
  },
  {
    "bill_numbers": [
      "2"
    ],
    "chamber": "h",
    "collection": "llhb",
    "committees": [
      "Committee of the Whole House"
    ],
    "congress": "007",
    "dates": [
      "18021221"
    ],
    "description": "Read the first and second time, and committed to a Committee of the whole House To-morrow. A Bill, To allow a drawback of duties on goods exported to New Orleans; and therein to amend the act intituled ''An act to regulate the collection of duties on imports and tonnage.''",
    "page": "",
    "session": "002",
    "tiff_filename": "00090000.tif",
    "volume": "021"
  },
  {
    "bill_numbers": [
      "3"
    ],
    "chamber": "h",
    "collection": "llhb",
    "committees": [
      "Committee of the Whole House"
    ],
    "congress": "007",
    "dates": [
      "18030103"
    ],
    "description": "Read the first and second time, and ordered to be committed to a Committee of the whole House To-morrow. A Bill, Making a partial appropriation for the Naval service, during the year one thousand eight hundred and three.",
    "page": "",
    "session": "002",
    "tiff_filename": "00100000.tif",
    "volume": "021"
  },
  {
    "bill_numbers": [
      "4"
    ],
    "chamber": "h",
    "collection": "llhb",
    "committees": [
      "Committee of the Whole House"
    ],
    "congress": "007",
    "dates": [
      "18030103"
    ],
    "description": "Read the first and second time, and ordered to be committed to a Committee of the whole House To-morrow. A Bill, Making appropriations for the Military establishment of the United States, in the year one thousand eight hundred and three.",
    "page": "",
    "session": "002",
    "tiff_filename": "00110000.tif",
    "volume": "021"
  },
  {
    "bill_numbers": [
      "4"
    ],
    "chamber": "h",
    "collection": "llhb",
    "committees": [],
    "congress": "007",
    "dates": [
      "18030103"
    ],
    "description": "",
    "page": "2",
    "session": "002",
    "tiff_filename": "00120002.tif",
    "volume": "021"
  },
  {
    "bill_numbers": [
      "5"
    ],
    "chamber": "h",
    "collection": "llhb",
    "committees": [
      "Committee of the Whole House"
    ],
    "congress": "007",
    "dates": [
      "18030111"
    ],
    "description": "Read the first and second time, and ordered to be committed to a Committee of the whole House on Thursday next. A Bill, For the relief of Insolvent Debtors, within the District of Columbia.",
    "page": "",
    "session": "002",
    "tiff_filename": "00130000.tif",
    "volume": "021"
  },
  {
    "bill_numbers": [
      "5"
    ],
    "chamber": "h",
    "collection": "llhb",
    "committees": [],
    "congress": "007",
    "dates": [
      "18030111"
    ],
    "description": "",
    "page": "2",
    "session": "002",
    "tiff_filename": "00140002.tif",
    "volume": "021"
  },
  {
    "bill_numbers": [
      "5"
    ],
    "chamber": "h",
    "collection": "llhb",
    "committees": [],
    "congress": "007",
    "dates": [
      "18030111"
    ],
    "description": "",
    "page": "3",
    "session": "002",
    "tiff_filename": "00150003.tif",
    "volume": "021"
  },
  {
    "bill_numbers": [
      "5"
    ],
    "chamber": "h",
    "collection": "llhb",
    "committees": [],
    "congress": "007",
    "dates": [
      "18030111"
    ],
    "description": "",
    "page": "4",
    "session": "002",
    "tiff_filename": "00160004.tif",
    "volume": "021"
  },
  {
    "bill_numbers": [
      "5"
    ],
    "chamber": "h",
    "collection": "llhb",
    "committees": [],
    "congress": "007",
    "dates": [
      "18030111"
    ],
    "description": "",
    "page": "5",
    "session": "002",
    "tiff_filename": "00170005.tif",
    "volume": "021"
  },
  {
    "bill_numbers": [
      "5"
    ],
    "chamber": "h",
    "collection": "llhb",
    "committees": [],
    "congress": "007",
    "dates": [
      "18030111"
    ],
    "description": "",
    "page": "6",
    "session": "002",
    "tiff_filename": "00180006.tif",
    "volume": "021"
  },
  {
    "bill_numbers": [
      "5"
    ],
    "chamber": "h",
    "collection": "llhb",
    "committees": [],
    "congress": "007",
    "dates": [
      "18030111"
    ],
    "description": "",
    "page": "7",
    "session": "002",
    "tiff_filename": "00190007.tif",
    "volume": "021"
  },
  {
    "bill_numbers": [
      "5"
    ],
    "chamber": "h",
    "collection": "llhb",
    "committees": [],
    "congress": "007",
    "dates": [
      "18030111"
    ],
    "description": "",
    "page": "8",
    "session": "002",
    "tiff_filename": "00200008.tif",
    "volume": "021"
  },
  {
    "bill_numbers": [
      "6"
    ],
    "chamber": "h",
    "collection": "llhb",
    "committees": [
      "Committee of the Whole House"
    ],
    "congress": "007",
    "dates": [
      "18030113"
    ],
    "description": "Read the first and second time, and ordered to be committed to a Committee of the whole House to-morrow. A Bill, For the relief of Henry Messonnier.",
    "page": "",
    "session": "002",
    "tiff_filename": "00210000.tif",
    "volume": "021"
  },
  {
    "bill_numbers": [
      "7"
    ],
    "chamber": "h",
    "collection": "llhb",
    "committees": [
      "Committee of the Whole House"
    ],
    "congress": "007",
    "dates": [
      "18030113"
    ],
    "description": "Read the first and second time, and ordered to be committed to a Committee of the whole House on Monday next. A Bill, For incorporating an Insurance Company in the City of Washington.",
    "page": "",
    "session": "002",
    "tiff_filename": "00220000.tif",
    "volume": "021"
  },
  {
    "bill_numbers": [
      "7"
    ],
    "chamber": "h",
    "collection": "llhb",
    "committees": [],
    "congress": "007",
    "dates": [
      "18030113"
    ],
    "description": "",
    "page": "2",
    "session": "002",
    "tiff_filename": "00230002.tif",
    "volume": "021"
  },
  {
    "bill_numbers": [
      "7"
    ],
    "chamber": "h",
    "collection": "llhb",
    "committees": [],
    "congress": "007",
    "dates": [
      "18030113"
    ],
    "description": "",
    "page": "3",
    "session": "002",
    "tiff_filename": "00240003.tif",
    "volume": "021"
  },
  {
    "bill_numbers": [
      "7"
    ],
    "chamber": "h",
    "collection": "llhb",
    "committees": [],
    "congress": "007",
    "dates": [
      "18030113"
    ],
    "description": "",
    "page": "4",
    "session": "002",
    "tiff_filename": "00250004.tif",
    "volume": "021"
  },
  {
    "bill_numbers": [
      "7"
    ],
    "chamber": "h",
    "collection": "llhb",
    "committees": [],
    "congress": "007",
    "dates": [
      "18030113"
    ],
    "description": "",
    "page": "5",
    "session": "002",
    "tiff_filename": "00260005.tif",
    "volume": "021"
  },
  {
    "bill_numbers": [
      "7"
    ],
    "chamber": "h",
    "collection": "llhb",
    "committees": [],
    "congress": "007",
    "dates": [
      "18030113"
    ],
    "description": "",
    "page": "6",
    "session": "002",
    "tiff_filename": "00270006.tif",
    "volume": "021"
  },
  {
    "bill_numbers": [
      "7"
    ],
    "chamber": "h",
    "collection": "llhb",
    "committees": [],
    "congress": "007",
    "dates": [
      "18030113"
    ],
    "description": "",
    "page": "7",
    "session": "002",
    "tiff_filename": "00280007.tif",
    "volume": "021"
  },
  {
    "bill_numbers": [
      "7"
    ],
    "chamber": "h",
    "collection": "llhb",
    "committees": [],
    "congress": "007",
    "dates": [
      "18030113"
    ],
    "description": "",
    "page": "8",
    "session": "002",
    "tiff_filename": "00290008.tif",
    "volume": "021"
  },
  {
    "bill_numbers": [
      "7"
    ],
    "chamber": "h",
    "collection": "llhb",
    "committees": [],
    "congress": "007",
    "dates": [
      "18030113"
    ],
    "description": "",
    "page": "9",
    "session": "002",
    "tiff_filename": "00300009.tif",
    "volume": "021"
  },
  {
    "bill_numbers": [
      "7"
    ],
    "chamber": "h",
    "collection": "llhb",
    "committees": [],
    "congress": "007",
    "dates": [
      "18030113"
    ],
    "description": "",
    "page": "10",
    "session": "002",
    "tiff_filename": "00310010.tif",
    "volume": "021"
  },
  {
    "bill_numbers": [
      "7"
    ],
    "chamber": "h",
    "collection": "llhb",
    "committees": [],
    "congress": "007",
    "dates": [
      "18030113"
    ],
    "description": "",
    "page": "11",
    "session": "002",
    "tiff_filename": "00320011.tif",
    "volume": "021"
  },
  {
    "bill_numbers": [
      "8"
    ],
    "chamber": "h",
    "collection": "llhb",
    "committees": [
      "Committee of the Whole House"
    ],
    "congress": "007",
    "dates": [
      "18030113"
    ],
    "description": "Read the first and second time, and ordered to be committed to a Committee of the whole House to-morrow. A Bill, For the relief of Hugh Alexander, and others.",
    "page": "",
    "session": "002",
    "tiff_filename": "00330000.tif",
    "volume": "021"
  },
  {
    "bill_numbers": [
      "8"
    ],
    "chamber": "h",
    "collection": "llhb",
    "committees": [],
    "congress": "007",
    "dates": [
      "18030113"
    ],
    "description": "",
    "page": "2",
    "session": "002",
    "tiff_filename": "00340002.tif",
    "volume": "021"
  },
  {
    "bill_numbers": [
      "9"
    ],
    "chamber": "h",
    "collection": "llhb",
    "committees": [
      "Committee of the Whole House"
    ],
    "congress": "007",
    "dates": [
      "18030114"
    ],
    "description": "Read the first and second time, and ordered to be committed to a Committee of the whole House on Tuesday next. A Bill, Additional to and amendatory of an act, intituled, ''An act to incorporate the inhabitants of the city of Washington, in the district of Columbia.''",
    "page": "",
    "session": "002",
    "tiff_filename": "00350000.tif",
    "volume": "021"
  },
  {
    "bill_numbers": [
      "9"
    ],
    "chamber": "h",
    "collection": "llhb",
    "committees": [],
    "congress": "007",
    "dates": [
      "18030114"
    ],
    "description": "",
    "page": "2",
    "session": "002",
    "tiff_filename": "00360002.tif",
    "volume": "021"
  },
  {
    "bill_numbers": [
      "9"
    ],
    "chamber": "h",
    "collection": "llhb",
    "committees": [],
    "congress": "007",
    "dates": [
      "18030114"
    ],
    "description": "",
    "page": "3",
    "session": "002",
    "tiff_filename": "00370003.tif",
    "volume": "021"
  },
  {
    "bill_numbers": [
      "9"
    ],
    "chamber": "h",
    "collection": "llhb",
    "committees": [],
    "congress": "007",
    "dates": [
      "18030114"
    ],
    "description": "",
    "page": "4",
    "session": "002",
    "tiff_filename": "00380004.tif",
    "volume": "021"
  },
  {
    "bill_numbers": [
      "9"
    ],
    "chamber": "h",
    "collection": "llhb",
    "committees": [],
    "congress": "007",
    "dates": [
      "18030114"
    ],
    "description": "",
    "page": "5",
    "session": "002",
    "tiff_filename": "00390005.tif",
    "volume": "021"
  },
  {
    "bill_numbers": [
      "10"
    ],
    "chamber": "h",
    "collection": "llhb",
    "committees": [
      "Committee of the Whole House"
    ],
    "congress": "007",
    "dates": [
      "18030114"
    ],
    "description": "Read the first and second time, and ordered to be committed to a Committee of the whole House on Tuesday next. A Bill, To lay out and open a new public road in the county of Washington, in the District of Columbia.",
    "page": "",
    "session": "002",
    "tiff_filename": "00400000.tif",
    "volume": "021"
  },
  {
    "bill_numbers": [
      "10"
    ],
    "chamber": "h",
    "collection": "llhb",
    "committees": [],
    "congress": "007",
    "dates": [
      "18030114"
    ],
    "description": "",
    "page": "2",
    "session": "002",
    "tiff_filename": "00410002.tif",
    "volume": "021"
  },
  {
    "bill_numbers": [
      "11"
    ],
    "chamber": "h",
    "collection": "llhb",
    "committees": [
      "Committee of the Whole House"
    ],
    "congress": "007",
    "dates": [
      "18030114"
    ],
    "description": "Read the first and second time, and ordered to be committed to a Committee of the whole House on Monday next. A Bill, For the relief of the sufferers by fire, in the town of Portsmouth.",
    "page": "",
    "session": "002",
    "tiff_filename": "00420000.tif",
    "volume": "021"
  },
  {
    "bill_numbers": [
      "12"
    ],
    "chamber": "h",
    "collection": "llhb",
    "committees": [
      "Committee of the Whole House"
    ],
    "congress": "007",
    "dates": [
      "18030119"
    ],
    "description": "Read the first and second time, and ordered to be committed to a Committee of the whole House on Monday next. A Bill, For the importation of Ordnance, Arms, &c.",
    "page": "",
    "session": "002",
    "tiff_filename": "00430000.tif",
    "volume": "021"
  },
  {
    "bill_numbers": [
      "13"
    ],
    "chamber": "h",
    "collection": "llhb",
    "committees": [
      "Committee of the Whole House"
    ],
    "congress": "007",
    "dates": [
      "18030119"
    ],
    "description": "Read the first and second time, and ordered to be committed to a Committee of the whole House on Monday next. A Bill, For the encouragement of Learning, and for the promotion of Useful Arts.",
    "page": "",
    "session": "002",
    "tiff_filename": "00440000.tif",
    "volume": "021"
  },
  {
    "bill_numbers": [
      "13"
    ],
    "chamber": "h",
    "collection": "llhb",
    "committees": [],
    "congress": "007",
    "dates": [
      "18030119"
    ],
    "description": "",
    "page": "2",
    "session": "002",
    "tiff_filename": "00450002.tif",
    "volume": "021"
  },
  {
    "bill_numbers": [
      "13"
    ],
    "chamber": "h",
    "collection": "llhb",
    "committees": [],
    "congress": "007",
    "dates": [
      "18030119"
    ],
    "description": "",
    "page": "3",
    "session": "002",
    "tiff_filename": "00460003.tif",
    "volume": "021"
  },
  {
    "bill_numbers": [
      "13"
    ],
    "chamber": "h",
    "collection": "llhb",
    "committees": [],
    "congress": "007",
    "dates": [
      "18030119"
    ],
    "description": "",
    "page": "4",
    "session": "002",
    "tiff_filename": "00470004.tif",
    "volume": "021"
  },
  {
    "bill_numbers": [
      "13"
    ],
    "chamber": "h",
    "collection": "llhb",
    "committees": [],
    "congress": "007",
    "dates": [
      "18030119"
    ],
    "description": "",
    "page": "5",
    "session": "002",
    "tiff_filename": "00480005.tif",
    "volume": "021"
  },
  {
    "bill_numbers": [
      "13"
    ],
    "chamber": "h",
    "collection": "llhb",
    "committees": [],
    "congress": "007",
    "dates": [
      "18030119"
    ],
    "description": "",
    "page": "6",
    "session": "002",
    "tiff_filename": "00490006.tif",
    "volume": "021"
  },
  {
    "bill_numbers": [
      "13"
    ],
    "chamber": "h",
    "collection": "llhb",
    "committees": [],
    "congress": "007",
    "dates": [
      "18030119"
    ],
    "description": "",
    "page": "7",
    "session": "002",
    "tiff_filename": "00500007.tif",
    "volume": "021"
  },
  {
    "bill_numbers": [
      "13"
    ],
    "chamber": "h",
    "collection": "llhb",
    "committees": [],
    "congress": "007",
    "dates": [
      "18030119"
    ],
    "description": "",
    "page": "8",
    "session": "002",
    "tiff_filename": "00510008.tif",
    "volume": "021"
  },
  {
    "bill_numbers": [
      "13"
    ],
    "chamber": "h",
    "collection": "llhb",
    "committees": [],
    "congress": "007",
    "dates": [
      "18030119"
    ],
    "description": "",
    "page": "9",
    "session": "002",
    "tiff_filename": "00520009.tif",
    "volume": "021"
  },
  {
    "bill_numbers": [
      "13"
    ],
    "chamber": "h",
    "collection": "llhb",
    "committees": [],
    "congress": "007",
    "dates": [
      "18030119"
    ],
    "description": "",
    "page": "10",
    "session": "002",
    "tiff_filename": "00530010.tif",
    "volume": "021"
  },
  {
    "bill_numbers": [
      "13"
    ],
    "chamber": "h",
    "collection": "llhb",
    "committees": [],
    "congress": "007",
    "dates": [
      "18030119"
    ],
    "description": "",
    "page": "11",
    "session": "002",
    "tiff_filename": "00540011.tif",
    "volume": "021"
  },
  {
    "bill_numbers": [
      "13"
    ],
    "chamber": "h",
    "collection": "llhb",
    "committees": [],
    "congress": "007",
    "dates": [
      "18030119"
    ],
    "description": "",
    "page": "12",
    "session": "002",
    "tiff_filename": "00550012.tif",
    "volume": "021"
  },
  {
    "bill_numbers": [
      "13"
    ],
    "chamber": "h",
    "collection": "llhb",
    "committees": [],
    "congress": "007",
    "dates": [
      "18030119"
    ],
    "description": "",
    "page": "13",
    "session": "002",
    "tiff_filename": "00560013.tif",
    "volume": "021"
  },
  {
    "bill_numbers": [
      "13"
    ],
    "chamber": "h",
    "collection": "llhb",
    "committees": [],
    "congress": "007",
    "dates": [
      "18030119"
    ],
    "description": "",
    "page": "14",
    "session": "002",
    "tiff_filename": "00570014.tif",
    "volume": "021"
  },
  {
    "bill_numbers": [
      "13"
    ],
    "chamber": "h",
    "collection": "llhb",
    "committees": [],
    "congress": "007",
    "dates": [
      "18030119"
    ],
    "description": "",
    "page": "15",
    "session": "002",
    "tiff_filename": "00580015.tif",
    "volume": "021"
  },
  {
    "bill_numbers": [
      "14"
    ],
    "chamber": "h",
    "collection": "llhb",
    "committees": [
      "Committee of the Whole House"
    ],
    "congress": "007",
    "dates": [
      "18030124"
    ],
    "description": "Read the first and second time, and ordered to be committed to a Committee of the whole House on Thursday next. A Bill, Supplementary to the ''Act concerning Consuls and Vice-Consuls,'' and for the further protection of American Seaman.",
    "page": "",
    "session": "002",
    "tiff_filename": "00590000.tif",
    "volume": "021"
  },
  {
    "bill_numbers": [
      "14"
    ],
    "chamber": "h",
    "collection": "llhb",
    "committees": [],
    "congress": "007",
    "dates": [
      "18030124"
    ],
    "description": "",
    "page": "2",
    "session": "002",
    "tiff_filename": "00600002.tif",
    "volume": "021"
  },
  {
    "bill_numbers": [
      "14"
    ],
    "chamber": "h",
    "collection": "llhb",
    "committees": [],
    "congress": "007",
    "dates": [
      "18030124"
    ],
    "description": "",
    "page": "3",
    "session": "002",
    "tiff_filename": "00610003.tif",
    "volume": "021"
  },
  {
    "bill_numbers": [
      "14"
    ],
    "chamber": "h",
    "collection": "llhb",
    "committees": [],
    "congress": "007",
    "dates": [
      "18030124"
    ],
    "description": "",
    "page": "4",
    "session": "002",
    "tiff_filename": "00620004.tif",
    "volume": "021"
  },
  {
    "bill_numbers": [
      "14"
    ],
    "chamber": "h",
    "collection": "llhb",
    "committees": [],
    "congress": "007",
    "dates": [
      "18030124"
    ],
    "description": "",
    "page": "5",
    "session": "002",
    "tiff_filename": "00630005.tif",
    "volume": "021"
  },
  {
    "bill_numbers": [
      "14"
    ],
    "chamber": "h",
    "collection": "llhb",
    "committees": [],
    "congress": "007",
    "dates": [
      "18030124"
    ],
    "description": "",
    "page": "6",
    "session": "002",
    "tiff_filename": "00640006.tif",
    "volume": "021"
  },
  {
    "bill_numbers": [
      "15"
    ],
    "chamber": "h",
    "collection": "llhb",
    "committees": [
      "Committee of the Whole House"
    ],
    "congress": "007",
    "dates": [
      "18030125"
    ],
    "description": "Read the first and second time, and ordered to be committed to a Committee of the whole House on Monday next. A Bill, Making an appropriation for the preservation of Timber on the public Navy Yards, and for the improvement of the same.",
    "page": "",
    "session": "002",
    "tiff_filename": "00650000.tif",
    "volume": "021"
  },
  {
    "bill_numbers": [
      "16"
    ],
    "chamber": "h",
    "collection": "llhb",
    "committees": [
      "Committee of the Whole House"
    ],
    "congress": "007",
    "dates": [
      "18030125"
    ],
    "description": "Read the first and second time, and ordered to be committed to a Committee of the whole House to-morrow. A Bill, To make provisions for persons that have been disabled by known wounds received in the service of the United States, during the Revolutionary War.",
    "page": "",
    "session": "002",
    "tiff_filename": "00660000.tif",
    "volume": "021"
  },
  {
    "bill_numbers": [
      "16"
    ],
    "chamber": "h",
    "collection": "llhb",
    "committees": [],
    "congress": "007",
    "dates": [
      "18030125"
    ],
    "description": "",
    "page": "2",
    "session": "002",
    "tiff_filename": "00670002.tif",
    "volume": "021"
  },
  {
    "bill_numbers": [
      "17"
    ],
    "chamber": "h",
    "collection": "llhb",
    "committees": [
      "Committee of the Whole House"
    ],
    "congress": "007",
    "dates": [
      "18030126"
    ],
    "description": "Read the first and second time, and ordered to be committed to a Committee of the whole House to-morrow. A Bill, For the relief of William Ray, and John Follawell.",
    "page": "",
    "session": "002",
    "tiff_filename": "00680000.tif",
    "volume": "021"
  },
  {
    "bill_numbers": [
      "18"
    ],
    "chamber": "h",
    "collection": "llhb",
    "committees": [
      "Committee of the Whole House"
    ],
    "congress": "007",
    "dates": [
      "18030126"
    ],
    "description": "Read the first and second time, and ordered to be committed to a Committee of the whole House to-morrow. A Bill, In addition to an Act, intituled ''An Act fixing the Military peace establishment of the United States.''",
    "page": "",
    "session": "002",
    "tiff_filename": "00690000.tif",
    "volume": "021"
  },
  {
    "bill_numbers": [
      "18"
    ],
    "chamber": "h",
    "collection": "llhb",
    "committees": [],
    "congress": "007",
    "dates": [
      "18030126"
    ],
    "description": "",
    "page": "2",
    "session": "002",
    "tiff_filename": "00700002.tif",
    "volume": "021"
  },
  {
    "bill_numbers": [
      "19"
    ],
    "chamber": "h",
    "collection": "llhb",
    "committees": [
      "Committee of the Whole House"
    ],
    "congress": "007",
    "dates": [
      "18030126"
    ],
    "description": "Read the first and second time, and ordered to be committed to a Committee of the whole House on Friday next. A Bill, For the relief of the proprietors of the Salem Turnpike road in Massachusetts.",
    "page": "",
    "session": "002",
    "tiff_filename": "00710000.tif",
    "volume": "021"
  },
  {
    "bill_numbers": [
      "19"
    ],
    "chamber": "h",
    "collection": "llhb",
    "committees": [],
    "congress": "007",
    "dates": [
      "18030126"
    ],
    "description": "",
    "page": "2",
    "session": "002",
    "tiff_filename": "00720002.tif",
    "volume": "021"
  },
  {
    "bill_numbers": [
      "20"
    ],
    "chamber": "h",
    "collection": "llhb",
    "committees": [
      "Committee of the Whole House"
    ],
    "congress": "007",
    "dates": [
      "18030126"
    ],
    "description": "Read the first and second time, and ordered to be committed to a Committee of the whole House on Monday next. A Bill, To prevent the importation of Certain Persons, whose admission is prohibited by certain laws of the State Government.",
    "page": "",
    "session": "002",
    "tiff_filename": "00730000.tif",
    "volume": "021"
  },
  {
    "bill_numbers": [
      "20"
    ],
    "chamber": "h",
    "collection": "llhb",
    "committees": [],
    "congress": "007",
    "dates": [
      "18030126"
    ],
    "description": "",
    "page": "2",
    "session": "002",
    "tiff_filename": "00740002.tif",
    "volume": "021"
  },
  {
    "bill_numbers": [
      "20"
    ],
    "chamber": "h",
    "collection": "llhb",
    "committees": [],
    "congress": "007",
    "dates": [
      "18030126"
    ],
    "description": "",
    "page": "3",
    "session": "002",
    "tiff_filename": "00750003.tif",
    "volume": "021"
  },
  {
    "bill_numbers": [
      "21"
    ],
    "chamber": "h",
    "collection": "llhb",
    "committees": [
      "Committee of the Whole House"
    ],
    "congress": "007",
    "dates": [
      "18030126",
      "18030204"
    ],
    "description": "Read the first and second time, and ordered to be committed to a Committee of the whole House on Monday next. Amended, and ordered to be engrossed. A Bill, To prevent the importation of Certain Persons, whose admission is prohibited by certain laws of the State Governments.",
    "page": "",
    "session": "002",
    "tiff_filename": "00760000.tif",
    "volume": "021"
  },
  {
    "bill_numbers": [
      "21"
    ],
    "chamber": "h",
    "collection": "llhb",
    "committees": [],
    "congress": "007",
    "dates": [
      "18030126",
      "18030204"
    ],
    "description": "",
    "page": "2",
    "session": "002",
    "tiff_filename": "00770002.tif",
    "volume": "021"
  },
  {
    "bill_numbers": [
      "21"
    ],
    "chamber": "h",
    "collection": "llhb",
    "committees": [],
    "congress": "007",
    "dates": [
      "18030126",
      "18030204"
    ],
    "description": "",
    "page": "3",
    "session": "002",
    "tiff_filename": "00780003.tif",
    "volume": "021"
  },
  {
    "bill_numbers": [
      "22"
    ],
    "chamber": "h",
    "collection": "llhb",
    "committees": [
      "Committee of the Whole House"
    ],
    "congress": "007",
    "dates": [
      "18030127"
    ],
    "description": "Read the first and second time, and ordered to be committed to a Committee of the whole House to-morrow. A Bill, To amend an Act, intituled, ''An Act to amend the Judicial System of the United States.''",
    "page": "",
    "session": "002",
    "tiff_filename": "00790000.tif",
    "volume": "021"
  },
  {
    "bill_numbers": [
      "22"
    ],
    "chamber": "h",
    "collection": "llhb",
    "committees": [],
    "congress": "007",
    "dates": [
      "18030127"
    ],
    "description": "",
    "page": "2",
    "session": "002",
    "tiff_filename": "00800002.tif",
    "volume": "021"
  },
  {
    "bill_numbers": [
      "23"
    ],
    "chamber": "h",
    "collection": "llhb",
    "committees": [
      "Committee of the Whole House"
    ],
    "congress": "007",
    "dates": [
      "18030128"
    ],
    "description": "Read the first and second time, and ordered to be committed to a Committee of the whole House on Monday next. A Bill, To provide an additional Armament for the protection of the Seaman and Commerce of the United States.",
    "page": "",
    "session": "002",
    "tiff_filename": "00810000.tif",
    "volume": "021"
  },
  {
    "bill_numbers": [
      "23"
    ],
    "chamber": "h",
    "collection": "llhb",
    "committees": [],
    "congress": "007",
    "dates": [
      "18030128"
    ],
    "description": "",
    "page": "2",
    "session": "002",
    "tiff_filename": "00820002.tif",
    "volume": "021"
  },
  {
    "bill_numbers": [
      "24"
    ],
    "chamber": "h",
    "collection": "llhb",
    "committees": [
      "Committee of the Whole House"
    ],
    "congress": "007",
    "dates": [
      "18030201"
    ],
    "description": "Read the first and second time, and ordered to be committed to a Committee of the whole House to-morrow. A Bill, To prolong, the continuance of the Mint of Philadelphia.",
    "page": "",
    "session": "002",
    "tiff_filename": "00830000.tif",
    "volume": "021"
  },
  {
    "bill_numbers": [
      "25"
    ],
    "chamber": "h",
    "collection": "llhb",
    "committees": [
      "Committee of the Whole House"
    ],
    "congress": "007",
    "dates": [
      "18030202"
    ],
    "description": "Read the first and second time, and ordered to be committed to a Committee of the whole House to-morrow. A Bill, For the relief of Moses White.",
    "page": "",
    "session": "002",
    "tiff_filename": "00840000.tif",
    "volume": "021"
  },
  {
    "bill_numbers": [
      "25"
    ],
    "chamber": "h",
    "collection": "llhb",
    "committees": [],
    "congress": "007",
    "dates": [
      "18030202"
    ],
    "description": "",
    "page": "2",
    "session": "002",
    "tiff_filename": "00850002.tif",
    "volume": "021"
  },
  {
    "bill_numbers": [
      "26"
    ],
    "chamber": "h",
    "collection": "llhb",
    "committees": [
      "Committee of the Whole House"
    ],
    "congress": "007",
    "dates": [
      "18030203"
    ],
    "description": "Read the first and second time, and ordered to be committed to a Committee of the whole House on Saturday next. A Bill, To provide for the granting of Clearances to Ships or Vessels of the United States, lying in the river Mississippi, south of the southern boundary of the United States, and therein to amend an act, intituled, ''An Act to regulate the Collection of Duties on Imports and Tonnage,'' and for other purposes.",
    "page": "",
    "session": "002",
    "tiff_filename": "00860000.tif",
    "volume": "021"
  },
  {
    "bill_numbers": [
      "26"
    ],
    "chamber": "h",
    "collection": "llhb",
    "committees": [],
    "congress": "007",
    "dates": [
      "18030203"
    ],
    "description": "",
    "page": "2",
    "session": "002",
    "tiff_filename": "00870002.tif",
    "volume": "021"
  },
  {
    "bill_numbers": [
      "26"
    ],
    "chamber": "h",
    "collection": "llhb",
    "committees": [],
    "congress": "007",
    "dates": [
      "18030203"
    ],
    "description": "",
    "page": "3",
    "session": "002",
    "tiff_filename": "00880003.tif",
    "volume": "021"
  },
  {
    "bill_numbers": [
      "26"
    ],
    "chamber": "h",
    "collection": "llhb",
    "committees": [],
    "congress": "007",
    "dates": [
      "18030203"
    ],
    "description": "",
    "page": "4",
    "session": "002",
    "tiff_filename": "00890004.tif",
    "volume": "021"
  },
  {
    "bill_numbers": [
      "27"
    ],
    "chamber": "h",
    "collection": "llhb",
    "committees": [
      "Committee of the Whole House"
    ],
    "congress": "007",
    "dates": [
      "18030203"
    ],
    "description": "Read the first and second time, and ordered to be committed to a Committee of the whole House on Saturday next. A Bill, Supplementary to the Act intituled ''An Act providing passports for the ships and vessels of the United States.''",
    "page": "",
    "session": "002",
    "tiff_filename": "00900000.tif",
    "volume": "021"
  },
  {
    "bill_numbers": [
      "27"
    ],
    "chamber": "h",
    "collection": "llhb",
    "committees": [],
    "congress": "007",
    "dates": [
      "18030203"
    ],
    "description": "",
    "page": "2",
    "session": "002",
    "tiff_filename": "00910002.tif",
    "volume": "021"
  },
  {
    "bill_numbers": [
      "28"
    ],
    "chamber": "h",
    "collection": "llhb",
    "committees": [
      "Committee of the Whole House"
    ],
    "congress": "007",
    "dates": [
      "18030207"
    ],
    "description": "Read the first and second time, and ordered to be committed to a Committee of the whole House on Wednesday next. A Bill, To make provision for Person that have been Disabled by known Wounds received in the actual service of the United States, during the Revolutionary War.",
    "page": "",
    "session": "002",
    "tiff_filename": "00920000.tif",
    "volume": "021"
  },
  {
    "bill_numbers": [
      "28"
    ],
    "chamber": "h",
    "collection": "llhb",
    "committees": [],
    "congress": "007",
    "dates": [
      "18030207"
    ],
    "description": "",
    "page": "2",
    "session": "002",
    "tiff_filename": "00930002.tif",
    "volume": "021"
  },
  {
    "bill_numbers": [
      "28"
    ],
    "chamber": "h",
    "collection": "llhb",
    "committees": [],
    "congress": "007",
    "dates": [
      "18030207"
    ],
    "description": "",
    "page": "3",
    "session": "002",
    "tiff_filename": "00940003.tif",
    "volume": "021"
  },
  {
    "bill_numbers": [
      "28"
    ],
    "chamber": "h",
    "collection": "llhb",
    "committees": [],
    "congress": "007",
    "dates": [
      "18030207"
    ],
    "description": "",
    "page": "4",
    "session": "002",
    "tiff_filename": "00950004.tif",
    "volume": "021"
  },
  {
    "bill_numbers": [
      "29"
    ],
    "chamber": "h",
    "collection": "llhb",
    "committees": [
      "Committee of the Whole House"
    ],
    "congress": "007",
    "dates": [
      "18030207"
    ],
    "description": "Read the first and second time, and referred to the committee of the whole House, to whom was, this day, committed ''so much of the message of the President of the United States, of the 15th December last, as relates to the Militia Institution of the United States.'' A Bill, In addition to an act, intituled, ''An Act more effectually to provide for the National defence, by establishing an Uniform Militia throughout the United States.''",
    "page": "",
    "session": "002",
    "tiff_filename": "00960000.tif",
    "volume": "021"
  },
  {
    "bill_numbers": [
      "29"
    ],
    "chamber": "h",
    "collection": "llhb",
    "committees": [],
    "congress": "007",
    "dates": [
      "18030207"
    ],
    "description": "",
    "page": "2",
    "session": "002",
    "tiff_filename": "00970002.tif",
    "volume": "021"
  },
  {
    "bill_numbers": [
      "30"
    ],
    "chamber": "h",
    "collection": "llhb",
    "committees": [
      "Committee of the Whole House"
    ],
    "congress": "007",
    "dates": [
      "18030208"
    ],
    "description": "Read the first and second time, and ordered to be committed to a Committee of the whole House on Friday next. A Bill, Further to alter and establish certain Post Roads, and for other purposes.",
    "page": "",
    "session": "002",
    "tiff_filename": "00980000.tif",
    "volume": "021"
  },
  {
    "bill_numbers": [
      "30"
    ],
    "chamber": "h",
    "collection": "llhb",
    "committees": [],
    "congress": "007",
    "dates": [
      "18030208"
    ],
    "description": "",
    "page": "2",
    "session": "002",
    "tiff_filename": "00990002.tif",
    "volume": "021"
  },
  {
    "bill_numbers": [
      "30"
    ],
    "chamber": "h",
    "collection": "llhb",
    "committees": [],
    "congress": "007",
    "dates": [
      "18030208"
    ],
    "description": "",
    "page": "3",
    "session": "002",
    "tiff_filename": "01000003.tif",
    "volume": "021"
  },
  {
    "bill_numbers": [
      "31"
    ],
    "chamber": "h",
    "collection": "llhb",
    "committees": [
      "Committee of the Whole House"
    ],
    "congress": "007",
    "dates": [
      "18030210"
    ],
    "description": "Read the first and second time, and ordered to be committed to a Committee of the whole House on Monday next. A Bill, For establishing the Government of the Territory of Columbia.",
    "page": "",
    "session": "002",
    "tiff_filename": "01010000.tif",
    "volume": "021"
  },
  {
    "bill_numbers": [
      "31"
    ],
    "chamber": "h",
    "collection": "llhb",
    "committees": [],
    "congress": "007",
    "dates": [
      "18030210"
    ],
    "description": "",
    "page": "2",
    "session": "002",
    "tiff_filename": "01020002.tif",
    "volume": "021"
  },
  {
    "bill_numbers": [
      "31"
    ],
    "chamber": "h",
    "collection": "llhb",
    "committees": [],
    "congress": "007",
    "dates": [
      "18030210"
    ],
    "description": "",
    "page": "3",
    "session": "002",
    "tiff_filename": "01030003.tif",
    "volume": "021"
  },
  {
    "bill_numbers": [
      "31"
    ],
    "chamber": "h",
    "collection": "llhb",
    "committees": [],
    "congress": "007",
    "dates": [
      "18030210"
    ],
    "description": "",
    "page": "4",
    "session": "002",
    "tiff_filename": "01040004.tif",
    "volume": "021"
  },
  {
    "bill_numbers": [
      "31"
    ],
    "chamber": "h",
    "collection": "llhb",
    "committees": [],
    "congress": "007",
    "dates": [
      "18030210"
    ],
    "description": "",
    "page": "5",
    "session": "002",
    "tiff_filename": "01050005.tif",
    "volume": "021"
  },
  {
    "bill_numbers": [
      "31"
    ],
    "chamber": "h",
    "collection": "llhb",
    "committees": [],
    "congress": "007",
    "dates": [
      "18030210"
    ],
    "description": "",
    "page": "6",
    "session": "002",
    "tiff_filename": "01060006.tif",
    "volume": "021"
  },
  {
    "bill_numbers": [
      "31"
    ],
    "chamber": "h",
    "collection": "llhb",
    "committees": [],
    "congress": "007",
    "dates": [
      "18030210"
    ],
    "description": "",
    "page": "7",
    "session": "002",
    "tiff_filename": "01070007.tif",
    "volume": "021"
  },
  {
    "bill_numbers": [
      "31"
    ],
    "chamber": "h",
    "collection": "llhb",
    "committees": [],
    "congress": "007",
    "dates": [
      "18030210"
    ],
    "description": "",
    "page": "8",
    "session": "002",
    "tiff_filename": "01080008.tif",
    "volume": "021"
  },
  {
    "bill_numbers": [
      "31"
    ],
    "chamber": "h",
    "collection": "llhb",
    "committees": [],
    "congress": "007",
    "dates": [
      "18030210"
    ],
    "description": "",
    "page": "9",
    "session": "002",
    "tiff_filename": "01090009.tif",
    "volume": "021"
  },
  {
    "bill_numbers": [
      "31"
    ],
    "chamber": "h",
    "collection": "llhb",
    "committees": [],
    "congress": "007",
    "dates": [
      "18030210"
    ],
    "description": "",
    "page": "10",
    "session": "002",
    "tiff_filename": "01100010.tif",
    "volume": "021"
  },
  {
    "bill_numbers": [
      "32"
    ],
    "chamber": "h",
    "collection": "llhb",
    "committees": [
      "Committee of the Whole House"
    ],
    "congress": "007",
    "dates": [
      "18030210"
    ],
    "description": "Read the first and second time, and ordered to be committed to a Committee of the whole House on Monday next. A Bill, To prevent the importation of certain Persons into certain States, where, by the laws thereof, their admission is prohibited",
    "page": "",
    "session": "002",
    "tiff_filename": "01110000.tif",
    "volume": "021"
  },
  {
    "bill_numbers": [
      "32"
    ],
    "chamber": "h",
    "collection": "llhb",
    "committees": [],
    "congress": "007",
    "dates": [
      "18030210"
    ],
    "description": "",
    "page": "2",
    "session": "002",
    "tiff_filename": "01120002.tif",
    "volume": "021"
  },
  {
    "bill_numbers": [
      "32"
    ],
    "chamber": "h",
    "collection": "llhb",
    "committees": [],
    "congress": "007",
    "dates": [
      "18030210"
    ],
    "description": "",
    "page": "3",
    "session": "002",
    "tiff_filename": "01130003.tif",
    "volume": "021"
  },
  {
    "bill_numbers": [
      "33"
    ],
    "chamber": "h",
    "collection": "llhb",
    "committees": [
      "Committee of the Whole House"
    ],
    "congress": "007",
    "dates": [
      "18030211"
    ],
    "description": "Read the first and second time, and ordered to be committed to a Committee of the whole House to-morrow. A Bill, For the relief of Samuel Corp.",
    "page": "",
    "session": "002",
    "tiff_filename": "01140000.tif",
    "volume": "021"
  },
  {
    "bill_numbers": [
      "33"
    ],
    "chamber": "h",
    "collection": "llhb",
    "committees": [],
    "congress": "007",
    "dates": [
      "18030211"
    ],
    "description": "",
    "page": "2",
    "session": "002",
    "tiff_filename": "01150002.tif",
    "volume": "021"
  },
  {
    "bill_numbers": [
      "34"
    ],
    "chamber": "h",
    "collection": "llhb",
    "committees": [
      "Committee of the Whole House",
      "Committee of Commerce and Manufactures"
    ],
    "congress": "007",
    "dates": [
      "18030212"
    ],
    "description": "Read the first and second time, and ordered to be committed to the Committee of the whole House, to whom was this day referred, the report of the Committee of Commerce and Manufactures, on the Petition of Thomas Storm, and others, Sugar Refiners of the City of New York. A Bill, To allow a drawback of Duty on Sugar Refined within the United States.",
    "page": "",
    "session": "002",
    "tiff_filename": "01160000.tif",
    "volume": "021"
  },
  {
    "bill_numbers": [
      "34"
    ],
    "chamber": "h",
    "collection": "llhb",
    "committees": [],
    "congress": "007",
    "dates": [
      "18030212"
    ],
    "description": "",
    "page": "2",
    "session": "002",
    "tiff_filename": "01170002.tif",
    "volume": "021"
  },
  {
    "bill_numbers": [
      "34"
    ],
    "chamber": "h",
    "collection": "llhb",
    "committees": [],
    "congress": "007",
    "dates": [
      "18030212"
    ],
    "description": "",
    "page": "3",
    "session": "002",
    "tiff_filename": "01180003.tif",
    "volume": "021"
  },
  {
    "bill_numbers": [
      "34"
    ],
    "chamber": "h",
    "collection": "llhb",
    "committees": [],
    "congress": "007",
    "dates": [
      "18030212"
    ],
    "description": "",
    "page": "4",
    "session": "002",
    "tiff_filename": "01190004.tif",
    "volume": "021"
  },
  {
    "bill_numbers": [
      "34"
    ],
    "chamber": "h",
    "collection": "llhb",
    "committees": [],
    "congress": "007",
    "dates": [
      "18030212"
    ],
    "description": "",
    "page": "5",
    "session": "002",
    "tiff_filename": "01200005.tif",
    "volume": "021"
  },
  {
    "bill_numbers": [
      "34"
    ],
    "chamber": "h",
    "collection": "llhb",
    "committees": [],
    "congress": "007",
    "dates": [
      "18030212"
    ],
    "description": "",
    "page": "6",
    "session": "002",
    "tiff_filename": "01210006.tif",
    "volume": "021"
  },
  {
    "bill_numbers": [
      "35"
    ],
    "chamber": "h",
    "collection": "llhb",
    "committees": [
      "Committee of the Whole House"
    ],
    "congress": "007",
    "dates": [
      "18030214"
    ],
    "description": "Read the first and second time, and ordered to be committed to a Committee of the whole House to-morrow. A Bill, Concerning the insurance of buildings, goods, and furniture, in the county of Alexandria, in the territory of Columbia.",
    "page": "",
    "session": "002",
    "tiff_filename": "01220000.tif",
    "volume": "021"
  },
  {
    "bill_numbers": [
      "35"
    ],
    "chamber": "h",
    "collection": "llhb",
    "committees": [],
    "congress": "007",
    "dates": [
      "18030214"
    ],
    "description": "",
    "page": "2",
    "session": "002",
    "tiff_filename": "01230002.tif",
    "volume": "021"
  },
  {
    "bill_numbers": [
      "36"
    ],
    "chamber": "h",
    "collection": "llhb",
    "committees": [
      "Committee of the Whole House"
    ],
    "congress": "007",
    "dates": [
      "18030214"
    ],
    "description": "Read the first and second time, and ordered to be committed to a Committee of the whole House on Thursday next. A Bill, More effectually to provide for the organization of the Militia of the District of Columbia.",
    "page": "",
    "session": "002",
    "tiff_filename": "01240000.tif",
    "volume": "021"
  },
  {
    "bill_numbers": [
      "36"
    ],
    "chamber": "h",
    "collection": "llhb",
    "committees": [],
    "congress": "007",
    "dates": [
      "18030214"
    ],
    "description": "",
    "page": "2",
    "session": "002",
    "tiff_filename": "01250002.tif",
    "volume": "021"
  },
  {
    "bill_numbers": [
      "36"
    ],
    "chamber": "h",
    "collection": "llhb",
    "committees": [],
    "congress": "007",
    "dates": [
      "18030214"
    ],
    "description": "",
    "page": "3",
    "session": "002",
    "tiff_filename": "01260003.tif",
    "volume": "021"
  },
  {
    "bill_numbers": [
      "36"
    ],
    "chamber": "h",
    "collection": "llhb",
    "committees": [],
    "congress": "007",
    "dates": [
      "18030214"
    ],
    "description": "",
    "page": "4",
    "session": "002",
    "tiff_filename": "01270004.tif",
    "volume": "021"
  },
  {
    "bill_numbers": [
      "36"
    ],
    "chamber": "h",
    "collection": "llhb",
    "committees": [],
    "congress": "007",
    "dates": [
      "18030214"
    ],
    "description": "",
    "page": "5",
    "session": "002",
    "tiff_filename": "01280005.tif",
    "volume": "021"
  },
  {
    "bill_numbers": [
      "36"
    ],
    "chamber": "h",
    "collection": "llhb",
    "committees": [],
    "congress": "007",
    "dates": [
      "18030214"
    ],
    "description": "",
    "page": "6",
    "session": "002",
    "tiff_filename": "01290006.tif",
    "volume": "021"
  },
  {
    "bill_numbers": [
      "36"
    ],
    "chamber": "h",
    "collection": "llhb",
    "committees": [],
    "congress": "007",
    "dates": [
      "18030214"
    ],
    "description": "",
    "page": "7",
    "session": "002",
    "tiff_filename": "01300007.tif",
    "volume": "021"
  },
  {
    "bill_numbers": [
      "36"
    ],
    "chamber": "h",
    "collection": "llhb",
    "committees": [],
    "congress": "007",
    "dates": [
      "18030214"
    ],
    "description": "",
    "page": "8",
    "session": "002",
    "tiff_filename": "01310008.tif",
    "volume": "021"
  },
  {
    "bill_numbers": [
      "36"
    ],
    "chamber": "h",
    "collection": "llhb",
    "committees": [],
    "congress": "007",
    "dates": [
      "18030214"
    ],
    "description": "",
    "page": "9",
    "session": "002",
    "tiff_filename": "01320009.tif",
    "volume": "021"
  },
  {
    "bill_numbers": [
      "36"
    ],
    "chamber": "h",
    "collection": "llhb",
    "committees": [],
    "congress": "007",
    "dates": [
      "18030214"
    ],
    "description": "",
    "page": "10",
    "session": "002",
    "tiff_filename": "01330010.tif",
    "volume": "021"
  },
  {
    "bill_numbers": [
      "36"
    ],
    "chamber": "h",
    "collection": "llhb",
    "committees": [],
    "congress": "007",
    "dates": [
      "18030214"
    ],
    "description": "",
    "page": "11",
    "session": "002",
    "tiff_filename": "01340011.tif",
    "volume": "021"
  },
  {
    "bill_numbers": [
      "36"
    ],
    "chamber": "h",
    "collection": "llhb",
    "committees": [],
    "congress": "007",
    "dates": [
      "18030214"
    ],
    "description": "",
    "page": "12",
    "session": "002",
    "tiff_filename": "01350012.tif",
    "volume": "021"
  },
  {
    "bill_numbers": [
      "36"
    ],
    "chamber": "h",
    "collection": "llhb",
    "committees": [],
    "congress": "007",
    "dates": [
      "18030214"
    ],
    "description": "",
    "page": "13",
    "session": "002",
    "tiff_filename": "01360013.tif",
    "volume": "021"
  },
  {
    "bill_numbers": [
      "36"
    ],
    "chamber": "h",
    "collection": "llhb",
    "committees": [],
    "congress": "007",
    "dates": [
      "18030214"
    ],
    "description": "",
    "page": "14",
    "session": "002",
    "tiff_filename": "01370014.tif",
    "volume": "021"
  },
  {
    "bill_numbers": [
      "36"
    ],
    "chamber": "h",
    "collection": "llhb",
    "committees": [],
    "congress": "007",
    "dates": [
      "18030214"
    ],
    "description": "",
    "page": "15",
    "session": "002",
    "tiff_filename": "01380015.tif",
    "volume": "021"
  },
  {
    "bill_numbers": [
      "36"
    ],
    "chamber": "h",
    "collection": "llhb",
    "committees": [],
    "congress": "007",
    "dates": [
      "18030214"
    ],
    "description": "",
    "page": "16",
    "session": "002",
    "tiff_filename": "01390016.tif",
    "volume": "021"
  },
  {
    "bill_numbers": [
      "36"
    ],
    "chamber": "h",
    "collection": "llhb",
    "committees": [],
    "congress": "007",
    "dates": [
      "18030214"
    ],
    "description": "",
    "page": "17",
    "session": "002",
    "tiff_filename": "01400017.tif",
    "volume": "021"
  },
  {
    "bill_numbers": [
      "36"
    ],
    "chamber": "h",
    "collection": "llhb",
    "committees": [],
    "congress": "007",
    "dates": [
      "18030214"
    ],
    "description": "",
    "page": "18",
    "session": "002",
    "tiff_filename": "01410018.tif",
    "volume": "021"
  },
  {
    "bill_numbers": [
      "36"
    ],
    "chamber": "h",
    "collection": "llhb",
    "committees": [],
    "congress": "007",
    "dates": [
      "18030214"
    ],
    "description": "",
    "page": "19",
    "session": "002",
    "tiff_filename": "01420019.tif",
    "volume": "021"
  },
  {
    "bill_numbers": [
      "36"
    ],
    "chamber": "h",
    "collection": "llhb",
    "committees": [],
    "congress": "007",
    "dates": [
      "18030214"
    ],
    "description": "",
    "page": "20",
    "session": "002",
    "tiff_filename": "01430020.tif",
    "volume": "021"
  },
  {
    "bill_numbers": [
      "36"
    ],
    "chamber": "h",
    "collection": "llhb",
    "committees": [],
    "congress": "007",
    "dates": [
      "18030214"
    ],
    "description": "",
    "page": "21",
    "session": "002",
    "tiff_filename": "01440021.tif",
    "volume": "021"
  },
  {
    "bill_numbers": [
      "36"
    ],
    "chamber": "h",
    "collection": "llhb",
    "committees": [],
    "congress": "007",
    "dates": [
      "18030214"
    ],
    "description": "",
    "page": "22",
    "session": "002",
    "tiff_filename": "01450022.tif",
    "volume": "021"
  },
  {
    "bill_numbers": [
      "36"
    ],
    "chamber": "h",
    "collection": "llhb",
    "committees": [],
    "congress": "007",
    "dates": [
      "18030214"
    ],
    "description": "",
    "page": "23",
    "session": "002",
    "tiff_filename": "01460023.tif",
    "volume": "021"
  },
  {
    "bill_numbers": [
      "36"
    ],
    "chamber": "h",
    "collection": "llhb",
    "committees": [],
    "congress": "007",
    "dates": [
      "18030214"
    ],
    "description": "",
    "page": "24",
    "session": "002",
    "tiff_filename": "01470024.tif",
    "volume": "021"
  },
  {
    "bill_numbers": [
      "36"
    ],
    "chamber": "h",
    "collection": "llhb",
    "committees": [],
    "congress": "007",
    "dates": [
      "18030214"
    ],
    "description": "",
    "page": "25",
    "session": "002",
    "tiff_filename": "01480025.tif",
    "volume": "021"
  },
  {
    "bill_numbers": [
      "36"
    ],
    "chamber": "h",
    "collection": "llhb",
    "committees": [],
    "congress": "007",
    "dates": [
      "18030214"
    ],
    "description": "",
    "page": "26",
    "session": "002",
    "tiff_filename": "01490026.tif",
    "volume": "021"
  },
  {
    "bill_numbers": [
      "36"
    ],
    "chamber": "h",
    "collection": "llhb",
    "committees": [],
    "congress": "007",
    "dates": [
      "18030214"
    ],
    "description": "",
    "page": "27",
    "session": "002",
    "tiff_filename": "01500027.tif",
    "volume": "021"
  },
  {
    "bill_numbers": [
      "36"
    ],
    "chamber": "h",
    "collection": "llhb",
    "committees": [],
    "congress": "007",
    "dates": [
      "18030214"
    ],
    "description": "",
    "page": "28",
    "session": "002",
    "tiff_filename": "01510028.tif",
    "volume": "021"
  },
  {
    "bill_numbers": [
      "36"
    ],
    "chamber": "h",
    "collection": "llhb",
    "committees": [],
    "congress": "007",
    "dates": [
      "18030214"
    ],
    "description": "",
    "page": "29",
    "session": "002",
    "tiff_filename": "01520029.tif",
    "volume": "021"
  },
  {
    "bill_numbers": [
      "37"
    ],
    "chamber": "h",
    "collection": "llhb",
    "committees": [
      "Committee of the Whole House"
    ],
    "congress": "007",
    "dates": [
      "18030214"
    ],
    "description": "Read the first and second time, and committed to a Committee of the whole House on Wednesday next. A Bill, In addition to the Act, intituled, ''An Act concerning the registering and recording of ships and vessels of the United States,'' and to the Act, intituled, ''An Act to regulate the collection of duties on imports and tonnage.''",
    "page": "",
    "session": "002",
    "tiff_filename": "01530000.tif",
    "volume": "021"
  },
  {
    "bill_numbers": [
      "37"
    ],
    "chamber": "h",
    "collection": "llhb",
    "committees": [],
    "congress": "007",
    "dates": [
      "18030214"
    ],
    "description": "",
    "page": "2",
    "session": "002",
    "tiff_filename": "01540002.tif",
    "volume": "021"
  },
  {
    "bill_numbers": [
      "37"
    ],
    "chamber": "h",
    "collection": "llhb",
    "committees": [],
    "congress": "007",
    "dates": [
      "18030214"
    ],
    "description": "",
    "page": "3",
    "session": "002",
    "tiff_filename": "01550003.tif",
    "volume": "021"
  },
  {
    "bill_numbers": [
      "38"
    ],
    "chamber": "h",
    "collection": "llhb",
    "committees": [
      "Committee of the Whole House"
    ],
    "congress": "007",
    "dates": [
      "18030215"
    ],
    "description": "Read the first and second time, and ordered to be committed to a Committee of the Whole House on Friday next. A Bill, Making an appropriation for the support of the Navy of the United States, for the year one thousand eight hundred and three.",
    "page": "",
    "session": "002",
    "tiff_filename": "01560000.tif",
    "volume": "021"
  },
  {
    "bill_numbers": [
      "38"
    ],
    "chamber": "h",
    "collection": "llhb",
    "committees": [],
    "congress": "007",
    "dates": [
      "18030215"
    ],
    "description": "",
    "page": "2",
    "session": "002",
    "tiff_filename": "01570002.tif",
    "volume": "021"
  },
  {
    "bill_numbers": [
      "38"
    ],
    "chamber": "h",
    "collection": "llhb",
    "committees": [],
    "congress": "007",
    "dates": [
      "18030215"
    ],
    "description": "",
    "page": "3",
    "session": "002",
    "tiff_filename": "01580003.tif",
    "volume": "021"
  },
  {
    "bill_numbers": [
      "38"
    ],
    "chamber": "h",
    "collection": "llhb",
    "committees": [],
    "congress": "007",
    "dates": [
      "18030215"
    ],
    "description": "",
    "page": "4",
    "session": "002",
    "tiff_filename": "01590004.tif",
    "volume": "021"
  },
  {
    "bill_numbers": [
      "39"
    ],
    "chamber": "h",
    "collection": "llhb",
    "committees": [
      "Committee of the Whole House"
    ],
    "congress": "007",
    "dates": [
      "18030215"
    ],
    "description": "Read the first and second time, and ordered to be committed to a Committee of the whole House on Thursday next. A Bill, For continuing in force a law, entitle ''An Act for establishing Trading houses with the Indian tribes.''",
    "page": "",
    "session": "002",
    "tiff_filename": "01600000.tif",
    "volume": "021"
  },
  {
    "bill_numbers": [
      "39"
    ],
    "chamber": "h",
    "collection": "llhb",
    "committees": [],
    "congress": "007",
    "dates": [
      "18030215"
    ],
    "description": "",
    "page": "2",
    "session": "002",
    "tiff_filename": "01610002.tif",
    "volume": "021"
  },
  {
    "bill_numbers": [
      "40"
    ],
    "chamber": "h",
    "collection": "llhb",
    "committees": [
      "Committee of the Whole House"
    ],
    "congress": "007",
    "dates": [
      "18030215"
    ],
    "description": "Read the first and second time, and ordered to be committed to a Committee of the whole House on Thursday next. A Bill, For erecting a Light-house at the entrance of Penobscot Bay, or any other place in its vicinity, that may be deemed preferable by the Secretary of the Treasury.",
    "page": "",
    "session": "002",
    "tiff_filename": "01620000.tif",
    "volume": "021"
  },
  {
    "bill_numbers": [
      "40"
    ],
    "chamber": "h",
    "collection": "llhb",
    "committees": [],
    "congress": "007",
    "dates": [
      "18030215"
    ],
    "description": "",
    "page": "",
    "session": "002",
    "tiff_filename": "01630002.tif",
    "volume": "021"
  },
  {
    "bill_numbers": [
      "41"
    ],
    "chamber": "h",
    "collection": "llhb",
    "committees": [
      "Committee of the Whole House"
    ],
    "congress": "007",
    "dates": [
      "18030216"
    ],
    "description": "Read the first and second time, and ordered to be committed to a Committee of the whole House on Friday next. A Bill, to establish a Building and Fire Insurance Company in the City of Washington.",
    "page": "",
    "session": "002",
    "tiff_filename": "01640000.tif",
    "volume": "021"
  },
  {
    "bill_numbers": [
      "41"
    ],
    "chamber": "h",
    "collection": "llhb",
    "committees": [],
    "congress": "007",
    "dates": [
      "18030216"
    ],
    "description": "",
    "page": "2",
    "session": "002",
    "tiff_filename": "01650002.tif",
    "volume": "021"
  },
  {
    "bill_numbers": [
      "41"
    ],
    "chamber": "h",
    "collection": "llhb",
    "committees": [],
    "congress": "007",
    "dates": [
      "18030216"
    ],
    "description": "",
    "page": "3",
    "session": "002",
    "tiff_filename": "01660003.tif",
    "volume": "021"
  },
  {
    "bill_numbers": [
      "41"
    ],
    "chamber": "h",
    "collection": "llhb",
    "committees": [],
    "congress": "007",
    "dates": [
      "18030216"
    ],
    "description": "",
    "page": "4",
    "session": "002",
    "tiff_filename": "01670004.tif",
    "volume": "021"
  },
  {
    "bill_numbers": [
      "41"
    ],
    "chamber": "h",
    "collection": "llhb",
    "committees": [],
    "congress": "007",
    "dates": [
      "18030216"
    ],
    "description": "",
    "page": "5",
    "session": "002",
    "tiff_filename": "01680005.tif",
    "volume": "021"
  },
  {
    "bill_numbers": [
      "41"
    ],
    "chamber": "h",
    "collection": "llhb",
    "committees": [],
    "congress": "007",
    "dates": [
      "18030216"
    ],
    "description": "",
    "page": "6",
    "session": "002",
    "tiff_filename": "01690006.tif",
    "volume": "021"
  },
  {
    "bill_numbers": [
      "41"
    ],
    "chamber": "h",
    "collection": "llhb",
    "committees": [],
    "congress": "007",
    "dates": [
      "18030216"
    ],
    "description": "",
    "page": "7",
    "session": "002",
    "tiff_filename": "01700007.tif",
    "volume": "021"
  },
  {
    "bill_numbers": [
      "42"
    ],
    "chamber": "h",
    "collection": "llhb",
    "committees": [
      "Committee of the Whole House"
    ],
    "congress": "007",
    "dates": [
      "18030216"
    ],
    "description": "Read the first and second time, and ordered to be committed to a Committee of the whole House To-morrow. A Bill, To revive and continue in force, an act in addition to an act, intituled, ''An act in addition to an act, regulating the grants of lands appropriated for military services, and for the society of the United Brethren, for propagating the Gospel among the Heathen.''",
    "page": "",
    "session": "002",
    "tiff_filename": "01710000.tif",
    "volume": "021"
  },
  {
    "bill_numbers": [
      "42"
    ],
    "chamber": "h",
    "collection": "llhb",
    "committees": [],
    "congress": "007",
    "dates": [
      "18030216"
    ],
    "description": "",
    "page": "2",
    "session": "002",
    "tiff_filename": "01720002.tif",
    "volume": "021"
  },
  {
    "bill_numbers": [
      "42"
    ],
    "chamber": "h",
    "collection": "llhb",
    "committees": [],
    "congress": "007",
    "dates": [
      "18030216"
    ],
    "description": "",
    "page": "3",
    "session": "002",
    "tiff_filename": "01730003.tif",
    "volume": "021"
  },
  {
    "bill_numbers": [
      "43"
    ],
    "chamber": "h",
    "collection": "llhb",
    "committees": [
      "Committee of the Whole House"
    ],
    "congress": "007",
    "dates": [
      "18030216"
    ],
    "description": "Read the first and second time, and ordered to be committed to a Committee of the whole House on Saturday next. A Bill, Making appropriations for the support of government, for the year one thousand eight hundred and three.",
    "page": "",
    "session": "002",
    "tiff_filename": "01740000.tif",
    "volume": "021"
  },
  {
    "bill_numbers": [
      "43"
    ],
    "chamber": "h",
    "collection": "llhb",
    "committees": [],
    "congress": "007",
    "dates": [
      "18030216"
    ],
    "description": "",
    "page": "2",
    "session": "002",
    "tiff_filename": "01750002.tif",
    "volume": "021"
  },
  {
    "bill_numbers": [
      "43"
    ],
    "chamber": "h",
    "collection": "llhb",
    "committees": [],
    "congress": "007",
    "dates": [
      "18030216"
    ],
    "description": "",
    "page": "3",
    "session": "002",
    "tiff_filename": "01760003.tif",
    "volume": "021"
  },
  {
    "bill_numbers": [
      "43"
    ],
    "chamber": "h",
    "collection": "llhb",
    "committees": [],
    "congress": "007",
    "dates": [
      "18030216"
    ],
    "description": "",
    "page": "4",
    "session": "002",
    "tiff_filename": "01770004.tif",
    "volume": "021"
  },
  {
    "bill_numbers": [
      "43"
    ],
    "chamber": "h",
    "collection": "llhb",
    "committees": [],
    "congress": "007",
    "dates": [
      "18030216"
    ],
    "description": "",
    "page": "5",
    "session": "002",
    "tiff_filename": "01780005.tif",
    "volume": "021"
  },
  {
    "bill_numbers": [
      "43"
    ],
    "chamber": "h",
    "collection": "llhb",
    "committees": [],
    "congress": "007",
    "dates": [
      "18030216"
    ],
    "description": "",
    "page": "6",
    "session": "002",
    "tiff_filename": "01790006.tif",
    "volume": "021"
  },
  {
    "bill_numbers": [
      "43"
    ],
    "chamber": "h",
    "collection": "llhb",
    "committees": [],
    "congress": "007",
    "dates": [
      "18030216"
    ],
    "description": "",
    "page": "7",
    "session": "002",
    "tiff_filename": "01800007.tif",
    "volume": "021"
  },
  {
    "bill_numbers": [
      "43"
    ],
    "chamber": "h",
    "collection": "llhb",
    "committees": [],
    "congress": "007",
    "dates": [
      "18030216"
    ],
    "description": "",
    "page": "8",
    "session": "002",
    "tiff_filename": "01810008.tif",
    "volume": "021"
  },
  {
    "bill_numbers": [
      "43"
    ],
    "chamber": "h",
    "collection": "llhb",
    "committees": [],
    "congress": "007",
    "dates": [
      "18030216"
    ],
    "description": "",
    "page": "9",
    "session": "002",
    "tiff_filename": "01820009.tif",
    "volume": "021"
  },
  {
    "bill_numbers": [
      "43"
    ],
    "chamber": "h",
    "collection": "llhb",
    "committees": [],
    "congress": "007",
    "dates": [
      "18030216"
    ],
    "description": "",
    "page": "10",
    "session": "002",
    "tiff_filename": "01830010.tif",
    "volume": "021"
  },
  {
    "bill_numbers": [
      "43"
    ],
    "chamber": "h",
    "collection": "llhb",
    "committees": [],
    "congress": "007",
    "dates": [
      "18030216"
    ],
    "description": "",
    "page": "11",
    "session": "002",
    "tiff_filename": "01840011.tif",
    "volume": "021"
  },
  {
    "bill_numbers": [
      "43"
    ],
    "chamber": "h",
    "collection": "llhb",
    "committees": [],
    "congress": "007",
    "dates": [
      "18030216"
    ],
    "description": "",
    "page": "12",
    "session": "002",
    "tiff_filename": "01850012.tif",
    "volume": "021"
  },
  {
    "bill_numbers": [
      "44"
    ],
    "chamber": "h",
    "collection": "llhb",
    "committees": [
      "Committee of the Whole House"
    ],
    "congress": "007",
    "dates": [
      "18030217"
    ],
    "description": "Read the first and second time, and ordered to be committed to a Committee of the whole House to-morrow. A Bill, In addition to an Act, intituled, ''An Act to establish an uniform rule of naturalization, and to repeal the acts heretofore passed on that subject.''",
    "page": "",
    "session": "002",
    "tiff_filename": "01860000.tif",
    "volume": "021"
  },
  {
    "bill_numbers": [
      "45"
    ],
    "chamber": "h",
    "collection": "llhb",
    "committees": [
      "Committee of the Whole House"
    ],
    "congress": "007",
    "dates": [
      "18030218"
    ],
    "description": "Read the first and second time, and ordered to be committed to a Committee of the whole House to-morrow. A Bill, To make Beaufort and Passamaquoddy, ports of entry and delivery; to make Easton, Nanjemoy, and Tiverton, ports of delivery; to change the name of the District of Nanjemoy to that of Saint Mary's; to authorize the establishment of a new collection District on Lake Ontario; and the appointment of a Surveyor at Nanjemoy.",
    "page": "",
    "session": "002",
    "tiff_filename": "01870000.tif",
    "volume": "021"
  },
  {
    "bill_numbers": [
      "45"
    ],
    "chamber": "h",
    "collection": "llhb",
    "committees": [],
    "congress": "007",
    "dates": [
      "18030218"
    ],
    "description": "",
    "page": "2",
    "session": "002",
    "tiff_filename": "01880002.tif",
    "volume": "021"
  },
  {
    "bill_numbers": [
      "45"
    ],
    "chamber": "h",
    "collection": "llhb",
    "committees": [],
    "congress": "007",
    "dates": [
      "18030218"
    ],
    "description": "",
    "page": "3",
    "session": "002",
    "tiff_filename": "01890003.tif",
    "volume": "021"
  },
  {
    "bill_numbers": [
      "46"
    ],
    "chamber": "h",
    "collection": "llhb",
    "committees": [
      "Committee of the Whole House"
    ],
    "congress": "007",
    "dates": [
      "18030218"
    ],
    "description": "Read the first and second time, and ordered to be committed to a Committee of the whole House to-morrow. A Bill, In addition to, and in modification of the propositions contained in the act, intituled, ''An Act to enable the people of the eastern division of the Territory north west of the river Ohio, to form a constitution and state government, and for the admission of such state into the Union, on an equal footing with the original states, and for other purposes.''",
    "page": "",
    "session": "002",
    "tiff_filename": "01900000.tif",
    "volume": "021"
  },
  {
    "bill_numbers": [
      "46"
    ],
    "chamber": "h",
    "collection": "llhb",
    "committees": [],
    "congress": "007",
    "dates": [
      "18030218"
    ],
    "description": "",
    "page": "2",
    "session": "002",
    "tiff_filename": "01910002.tif",
    "volume": "021"
  },
  {
    "bill_numbers": [
      "46"
    ],
    "chamber": "h",
    "collection": "llhb",
    "committees": [],
    "congress": "007",
    "dates": [
      "18030218"
    ],
    "description": "",
    "page": "3",
    "session": "002",
    "tiff_filename": "01920003.tif",
    "volume": "021"
  },
  {
    "bill_numbers": [
      "46"
    ],
    "chamber": "h",
    "collection": "llhb",
    "committees": [],
    "congress": "007",
    "dates": [
      "18030218"
    ],
    "description": "",
    "page": "4",
    "session": "002",
    "tiff_filename": "01930004.tif",
    "volume": "021"
  },
  {
    "bill_numbers": [
      "46"
    ],
    "chamber": "h",
    "collection": "llhb",
    "committees": [],
    "congress": "007",
    "dates": [
      "18030218"
    ],
    "description": "",
    "page": "5",
    "session": "002",
    "tiff_filename": "01940005.tif",
    "volume": "021"
  },
  {
    "bill_numbers": [
      "46"
    ],
    "chamber": "h",
    "collection": "llhb",
    "committees": [],
    "congress": "007",
    "dates": [
      "18030218"
    ],
    "description": "",
    "page": "6",
    "session": "002",
    "tiff_filename": "01950006.tif",
    "volume": "021"
  },
  {
    "bill_numbers": [
      "47"
    ],
    "chamber": "h",
    "collection": "llhb",
    "committees": [
      "Committee of the Whole House"
    ],
    "congress": "007",
    "dates": [
      "18030218"
    ],
    "description": "Read the first and second time, and ordered to be committed to a Committee of the whole House on Monday next. A Bill, to reduce the Marine Corps of the United States.",
    "page": "",
    "session": "002",
    "tiff_filename": "01960000.tif",
    "volume": "021"
  },
  {
    "bill_numbers": [
      "47"
    ],
    "chamber": "h",
    "collection": "llhb",
    "committees": [],
    "congress": "007",
    "dates": [
      "18030218"
    ],
    "description": "",
    "page": "2",
    "session": "002",
    "tiff_filename": "01970002.tif",
    "volume": "021"
  },
  {
    "bill_numbers": [
      "48"
    ],
    "chamber": "h",
    "collection": "llhb",
    "committees": [
      "Committee of the Whole House"
    ],
    "congress": "007",
    "dates": [
      "18030218"
    ],
    "description": "Read the first and second time, and ordered to be committed to a Committee of the whole House on Monday next. A Bill, For the relief of Joshua Harvey, and others.",
    "page": "",
    "session": "002",
    "tiff_filename": "01980000.tif",
    "volume": "021"
  },
  {
    "bill_numbers": [
      "48"
    ],
    "chamber": "h",
    "collection": "llhb",
    "committees": [],
    "congress": "007",
    "dates": [
      "18030218"
    ],
    "description": "",
    "page": "2",
    "session": "002",
    "tiff_filename": "01990002.tif",
    "volume": "021"
  },
  {
    "bill_numbers": [
      "49"
    ],
    "chamber": "h",
    "collection": "llhb",
    "committees": [
      "Committee of the Whole House"
    ],
    "congress": "007",
    "dates": [
      "18030219"
    ],
    "description": "Read the first and second time, and ordered to be committed to a Committee of the whole House on Monday next. A Bill, Concerning the Salt Springs on the waters of the Wabash River.",
    "page": "",
    "session": "002",
    "tiff_filename": "02000000.tif",
    "volume": "021"
  },
  {
    "bill_numbers": [
      "50"
    ],
    "chamber": "h",
    "collection": "llhb",
    "committees": [
      "Committee of the Whole House"
    ],
    "congress": "007",
    "dates": [
      "18030219"
    ],
    "description": "Read the first and second time, and ordered to be committed to a Committee of the whole House on Tuesday next. A Bill, Regulating the grants of land, and providing for the disposal of the lands of the United States, south of the State of Tennessee.",
    "page": "",
    "session": "002",
    "tiff_filename": "02010000.tif",
    "volume": "021"
  },
  {
    "bill_numbers": [
      "50"
    ],
    "chamber": "h",
    "collection": "llhb",
    "committees": [],
    "congress": "007",
    "dates": [
      "18030219"
    ],
    "description": "",
    "page": "2",
    "session": "002",
    "tiff_filename": "02020002.tif",
    "volume": "021"
  },
  {
    "bill_numbers": [
      "50"
    ],
    "chamber": "h",
    "collection": "llhb",
    "committees": [],
    "congress": "007",
    "dates": [
      "18030219"
    ],
    "description": "",
    "page": "3",
    "session": "002",
    "tiff_filename": "02030003.tif",
    "volume": "021"
  },
  {
    "bill_numbers": [
      "50"
    ],
    "chamber": "h",
    "collection": "llhb",
    "committees": [],
    "congress": "007",
    "dates": [
      "18030219"
    ],
    "description": "",
    "page": "4",
    "session": "002",
    "tiff_filename": "02040004.tif",
    "volume": "021"
  },
  {
    "bill_numbers": [
      "50"
    ],
    "chamber": "h",
    "collection": "llhb",
    "committees": [],
    "congress": "007",
    "dates": [
      "18030219"
    ],
    "description": "",
    "page": "5",
    "session": "002",
    "tiff_filename": "02050005.tif",
    "volume": "021"
  },
  {
    "bill_numbers": [
      "50"
    ],
    "chamber": "h",
    "collection": "llhb",
    "committees": [],
    "congress": "007",
    "dates": [
      "18030219"
    ],
    "description": "",
    "page": "6",
    "session": "002",
    "tiff_filename": "02060006.tif",
    "volume": "021"
  },
  {
    "bill_numbers": [
      "50"
    ],
    "chamber": "h",
    "collection": "llhb",
    "committees": [],
    "congress": "007",
    "dates": [
      "18030219"
    ],
    "description": "",
    "page": "7",
    "session": "002",
    "tiff_filename": "02070007.tif",
    "volume": "021"
  },
  {
    "bill_numbers": [
      "50"
    ],
    "chamber": "h",
    "collection": "llhb",
    "committees": [],
    "congress": "007",
    "dates": [
      "18030219"
    ],
    "description": "",
    "page": "8",
    "session": "002",
    "tiff_filename": "02080008.tif",
    "volume": "021"
  },
  {
    "bill_numbers": [
      "50"
    ],
    "chamber": "h",
    "collection": "llhb",
    "committees": [],
    "congress": "007",
    "dates": [
      "18030219"
    ],
    "description": "",
    "page": "9",
    "session": "002",
    "tiff_filename": "02090009.tif",
    "volume": "021"
  },
  {
    "bill_numbers": [
      "50"
    ],
    "chamber": "h",
    "collection": "llhb",
    "committees": [],
    "congress": "007",
    "dates": [
      "18030219"
    ],
    "description": "",
    "page": "10",
    "session": "002",
    "tiff_filename": "02100010.tif",
    "volume": "021"
  },
  {
    "bill_numbers": [
      "50"
    ],
    "chamber": "h",
    "collection": "llhb",
    "committees": [],
    "congress": "007",
    "dates": [
      "18030219"
    ],
    "description": "",
    "page": "11",
    "session": "002",
    "tiff_filename": "02110011.tif",
    "volume": "021"
  },
  {
    "bill_numbers": [
      "50"
    ],
    "chamber": "h",
    "collection": "llhb",
    "committees": [],
    "congress": "007",
    "dates": [
      "18030219"
    ],
    "description": "",
    "page": "12",
    "session": "002",
    "tiff_filename": "02120012.tif",
    "volume": "021"
  },
  {
    "bill_numbers": [
      "50"
    ],
    "chamber": "h",
    "collection": "llhb",
    "committees": [],
    "congress": "007",
    "dates": [
      "18030219"
    ],
    "description": "",
    "page": "13",
    "session": "002",
    "tiff_filename": "02130013.tif",
    "volume": "021"
  },
  {
    "bill_numbers": [
      "51"
    ],
    "chamber": "h",
    "collection": "llhb",
    "committees": [
      "Committee of the Whole House"
    ],
    "congress": "007",
    "dates": [
      "18030219"
    ],
    "description": "Read the first and second time, and ordered to be committed to a Committee of the whole House on Tuesday next. A Bill, for settling sundry claims to public lands of the United States, south of the State of Tennessee.",
    "page": "",
    "session": "002",
    "tiff_filename": "02140000.tif",
    "volume": "021"
  },
  {
    "bill_numbers": [
      "51"
    ],
    "chamber": "h",
    "collection": "llhb",
    "committees": [],
    "congress": "007",
    "dates": [
      "18030219"
    ],
    "description": "",
    "page": "2",
    "session": "002",
    "tiff_filename": "02150002.tif",
    "volume": "021"
  },
  {
    "bill_numbers": [
      "51"
    ],
    "chamber": "h",
    "collection": "llhb",
    "committees": [],
    "congress": "007",
    "dates": [
      "18030219"
    ],
    "description": "",
    "page": "3",
    "session": "002",
    "tiff_filename": "02160003.tif",
    "volume": "021"
  },
  {
    "bill_numbers": [
      "51"
    ],
    "chamber": "h",
    "collection": "llhb",
    "committees": [],
    "congress": "007",
    "dates": [
      "18030219"
    ],
    "description": "",
    "page": "4",
    "session": "002",
    "tiff_filename": "02170004.tif",
    "volume": "021"
  },
  {
    "bill_numbers": [
      "51"
    ],
    "chamber": "h",
    "collection": "llhb",
    "committees": [],
    "congress": "007",
    "dates": [
      "18030219"
    ],
    "description": "",
    "page": "5",
    "session": "002",
    "tiff_filename": "02180005.tif",
    "volume": "021"
  },
  {
    "bill_numbers": [
      "51"
    ],
    "chamber": "h",
    "collection": "llhb",
    "committees": [],
    "congress": "007",
    "dates": [
      "18030219"
    ],
    "description": "",
    "page": "6",
    "session": "002",
    "tiff_filename": "02190006.tif",
    "volume": "021"
  },
  {
    "bill_numbers": [
      "51"
    ],
    "chamber": "h",
    "collection": "llhb",
    "committees": [],
    "congress": "007",
    "dates": [
      "18030219"
    ],
    "description": "",
    "page": "7",
    "session": "002",
    "tiff_filename": "02200007.tif",
    "volume": "021"
  },
  {
    "bill_numbers": [
      "52"
    ],
    "chamber": "h",
    "collection": "llhb",
    "committees": [
      "Committee of the Whole House"
    ],
    "congress": "007",
    "dates": [
      "18030219",
      "18030221"
    ],
    "description": "Received, and ordered to lie on the Table. Read the first and second time, and ordered to be committed to a Committee of the whole House on Thursday next. A Bill, To Incorporate the Director of the Columbian Library Company.",
    "page": "",
    "session": "002",
    "tiff_filename": "02210000.tif",
    "volume": "021"
  },
  {
    "bill_numbers": [
      "52"
    ],
    "chamber": "h",
    "collection": "llhb",
    "committees": [],
    "congress": "007",
    "dates": [
      "18030219",
      "18030221"
    ],
    "description": "",
    "page": "2",
    "session": "002",
    "tiff_filename": "02220002.tif",
    "volume": "021"
  },
  {
    "bill_numbers": [
      "52"
    ],
    "chamber": "h",
    "collection": "llhb",
    "committees": [],
    "congress": "007",
    "dates": [
      "18030219",
      "18030221"
    ],
    "description": "",
    "page": "3",
    "session": "002",
    "tiff_filename": "02230003.tif",
    "volume": "021"
  },
  {
    "bill_numbers": [
      "52"
    ],
    "chamber": "h",
    "collection": "llhb",
    "committees": [],
    "congress": "007",
    "dates": [
      "18030219",
      "18030221"
    ],
    "description": "",
    "page": "4",
    "session": "002",
    "tiff_filename": "02240004.tif",
    "volume": "021"
  },
  {
    "bill_numbers": [
      "52"
    ],
    "chamber": "h",
    "collection": "llhb",
    "committees": [],
    "congress": "007",
    "dates": [
      "18030219",
      "18030221"
    ],
    "description": "",
    "page": "5",
    "session": "002",
    "tiff_filename": "02250005.tif",
    "volume": "021"
  },
  {
    "bill_numbers": [
      "53"
    ],
    "chamber": "h",
    "collection": "llhb",
    "committees": [
      "Committee of the Whole House"
    ],
    "congress": "007",
    "dates": [
      "18030225"
    ],
    "description": "Read the first and second time, and committed to the Committee of the whole House, to whom was this day referred, the report of a Committee appointed on the 15th instant on the subject of quarantine of vessels within the district of Columbia. A Bill, To regulate the Quarantine of ships and vessels in the port of Alexandria.",
    "page": "",
    "session": "002",
    "tiff_filename": "02260000.tif",
    "volume": "021"
  },
  {
    "bill_numbers": [
      "53"
    ],
    "chamber": "h",
    "collection": "llhb",
    "committees": [],
    "congress": "007",
    "dates": [
      "18030225"
    ],
    "description": "",
    "page": "2",
    "session": "002",
    "tiff_filename": "02270002.tif",
    "volume": "021"
  },
  {
    "bill_numbers": [
      "54"
    ],
    "chamber": "h",
    "collection": "llhb",
    "committees": [
      "Committee of the Whole House"
    ],
    "congress": "007",
    "dates": [
      "18030126"
    ],
    "description": "Mr. Jones's Motion. Referred to the Committee of the whole House, to whom was committed on the 10th instant, the report of the Committee of Commerce and Manufactures, on so much of the Message from the President of the United States of the 15th ultimo, as ''Relates to discriminating and countervailing duties, and the act of the British Parliament on that subject.''",
    "page": "",
    "session": "002",
    "tiff_filename": "02280000.tif",
    "volume": "021"
  }
]