[
  {
    "bill_numbers": [
      "H.R. 2"
    ],
    "chamber": "h",
    "collection": "llhb",
    "committees": [
      "Committee of the Whole House"
    ],
    "congress": 11,
    "dates": [
      "1810-12-12"
    ],
    "description": "Read the first and second time, and committed to a committee of the whole House to-morrow. A Bill For the apportionment of representatives among the several states, according to the third enumeration.",
    "pages": [
      {
        "image": "00010000.tif",
        "page": 1
      }
    ],
    "session": 3,
    "volume": 44
  },
  {
    "bill_numbers": [
      "H.R. 3"
    ],
    "chamber": "h",
    "collection": "llhb",
    "committees": [
      "Committee of the Whole House"
    ],
    "congress": 11,
    "dates": [
      "1810-12-14"
    ],
    "description": "Read the first and second time, and committed to a committee of the whole House on Wednesday next. A Bill Authorising the issuing of debentures in certain cases.",
    "pages": [
      {
        "image": "00020000.tif",
        "page": 1
      },
      {
        "image": "00030002.tif",
        "page": 2
      }
    ],
    "session": 3,
    "volume": 44
  },
  {
    "bill_numbers": [
      "H.R. 4"
    ],
    "chamber": "h",
    "collection": "llhb",
    "committees": [
      "Committee of the Whole House"
    ],
    "congress": 11,
    "dates": [
      "1810-12-17"
    ],
    "description": "Read the first and second time, and committed to a committee of the whole House to-morrow. A Bill To fix the compensation of the additional Assistant Post-master General.",
    "pages": [
      {
        "image": "00040000.tif",
        "page": 1
      }
    ],
    "session": 3,
    "volume": 44
  },
  {
    "bill_numbers": [
      "H.R. 5"
    ],
    "chamber": "h",
    "collection": "llhb",
    "committees": [
      "Committee of the Whole House"
    ],
    "congress": 11,
    "dates": [
      "1810-12-18"
    ],
    "description": "Read the first and second time, and committed to a committee of the whole House to-morrow. A Bill For the relief of George Armroyd and Company.",
    "pages": [
      {
        "image": "00050000.tif",
        "page": 1
      },
      {
        "image": "00060002.tif",
        "page": 2
      }
    ],
    "session": 3,
    "volume": 44
  },
  {
    "bill_numbers": [
      "H.R. 6"
    ],
    "chamber": "h",
    "collection": "llhb",
    "committees": [
      "Committee of the Whole House"
    ],
    "congress": 11,
    "dates": [
      "1810-12-19"
    ],
    "description": "Read the first and second time, and committed to a committee of the whole House on Friday next. A Bill To authorise the Secretary at War, to ascertain and settle, by the appointment of Commissioners, the exterior line of the Public Land at West Point, with the adjoining proprietor.",
    "pages": [
      {
        "image": "00070000.tif",
        "page": 1
      },
      {
        "image": "00080002.tif",
        "page": 2
      }
    ],
    "session": 3,
    "volume": 44
  },
  {
    "bill_numbers": [
      "H.R. 7"
    ],
    "chamber": "h",
    "collection": "llhb",
    "committees": [
      "Committee of the Whole House"
    ],
    "congress": 11,
    "dates": [
      "1810-12-19"
    ],
    "description": "Read the first and second time, and committed to a committee of the whole House on Friday next. A Bill For continuing the charter of the Bank of Alexandria, in the district of Columbia.",
    "pages": [
      {
        "image": "00090000.tif",
        "page": 1
      },
      {
        "image": "00100002.tif",
        "page": 2
      }
    ],
    "session": 3,
    "volume": 44
  },
  {
    "bill_numbers": [
      "H.R. 8"
    ],
    "chamber": "h",
    "collection": "llhb",
    "committees": [
      "Committee of the Whole House"
    ],
    "congress": 11,
    "dates": [
      "1810-12-19"
    ],
    "description": "Read the first and second time, and committed to a committee of the whole House, on Friday next. A Bill Providing for the final adjustment of claims to lands, and for the sale of the public lands in the territories of Orleans and Louisiana.",
    "pages": [
      {
        "image": "00110000.tif",
        "page": 1
      },
      {
        "image": "00120002.tif",
        "page": 2
      },
      {
        "image": "00130003.tif",
        "page": 3
      },
      {
        "image": "00140004.tif",
        "page": 4
      },
      {
        "image": "00150005.tif",
        "page": 5
      },
      {
        "image": "00160006.tif",
        "page": 6
      },
      {
        "image": "00170007.tif",
        "page": 7
      },
      {
        "image": "00180008.tif",
        "page": 8
      },
      {
        "image": "00190009.tif",
        "page": 9
      },
      {
        "image": "00200010.tif",
        "page": 10
      },
      {
        "image": "00210011.tif",
        "page": 11
      },
      {
        "image": "00220012.tif",
        "page": 12
      }
    ],
    "session": 3,
    "volume": 44
  },
  {
    "bill_numbers": [
      "H.R. 8"
    ],
    "chamber": "h",
    "collection": "llhb",
    "committees": [],
    "congress": 11,
    "dates": [
      "1810-12-24"
    ],
    "description": "Read, and ordered to be printed. Amendment Proposed by Mr. Poindexter, to the bill ''providing for the final adjustment of claims to lands, and for the sale of the public lands in the territories of Orleans and Louisiana.''",
    "pages": [
      {
        "image": "00230000.tif",
        "page": 1
      }
    ],
    "session": 3,
    "volume": 44
  },
  {
    "bill_numbers": [
      "H.R. 9"
    ],
    "chamber": "h",
    "collection": "llhb",
    "committees": [
      "Committee of the Whole House"
    ],
    "congress": 11,
    "dates": [
      "1810-12-19"
    ],
    "description": "Read the first and second time, and committed to a committee of the whole House on Friday next. A Bill To continue in force for a further time, the first section of the act, entitled ''An act further to protect the commerce and seamen of the United States against the Barbary powers.''",
    "pages": [
      {
        "image": "00240000.tif",
        "page": 1
      }
    ],
    "session": 3,
    "volume": 44
  },
  {
    "bill_numbers": [
      "H.R. 10"
    ],
    "chamber": "h",
    "collection": "llhb",
    "committees": [
      "Committee of the Whole House"
    ],
    "congress": 11,
    "dates": [
      "1810-12-19"
    ],
    "description": "Read the first and second time, and committed to a committee of the whole House on Friday next. A Bill Making an additional appropriation, to supply a deficiency in the appropriation for the relief and protection of distressed American Seamen, during the year one thousand eight hundred and ten.",
    "pages": [
      {
        "image": "00250000.tif",
        "page": 1
      }
    ],
    "session": 3,
    "volume": 44
  },
  {
    "bill_numbers": [
      "H.R. 11"
    ],
    "chamber": "h",
    "collection": "llhb",
    "committees": [
      "Committee of the Whole House"
    ],
    "congress": 11,
    "dates": [
      "1810-12-20"
    ],
    "description": "Read the first and second time, and committed to a committee of the whole House, on Monday next. A Bill To incorporate the subscribers to the Bank of Washington.",
    "pages": [
      {
        "image": "00260000.tif",
        "page": 1
      },
      {
        "image": "00270002.tif",
        "page": 2
      },
      {
        "image": "00280003.tif",
        "page": 3
      },
      {
        "image": "00290004.tif",
        "page": 4
      },
      {
        "image": "00300005.tif",
        "page": 5
      },
      {
        "image": "00310006.tif",
        "page": 6
      },
      {
        "image": "00320007.tif",
        "page": 7
      },
      {
        "image": "00330008.tif",
        "page": 8
      },
      {
        "image": "00340009.tif",
        "page": 9
      },
      {
        "image": "00350010.tif",
        "page": 10
      },
      {
        "image": "00360011.tif",
        "page": 11
      }
    ],
    "session": 3,
    "volume": 44
  },
  {
    "bill_numbers": [
      "H.R. 12"
    ],
    "chamber": "h",
    "collection": "llhb",
    "committees": [
      "Committee of the Whole House"
    ],
    "congress": 11,
    "dates": [
      "1810-12-20"
    ],
    "description": "Read the first and second time, and committed to a committee of the whole House on Tuesday next. A Bill For incorporating the Protestant Episcopal Church in the town of Alexandria, in the District of Columbia.",
    "pages": [
      {
        "image": "00370000.tif",
        "page": 1
      },
      {
        "image": "00380002.tif",
        "page": 2
      },
      {
        "image": "00390003.tif",
        "page": 3
      },
      {
        "image": "00400004.tif",
        "page": 4
      },
      {
        "image": "00410005.tif",
        "page": 5
      },
      {
        "image": "00420006.tif",
        "page": 6
      },
      {
        "image": "00430007.tif",
        "page": 7
      }
    ],
    "session": 3,
    "volume": 44
  },
  {
    "bill_numbers": [
      "H.R. 13"
    ],
    "chamber": "h",
    "collection": "llhb",
    "committees": [
      "Committee of the Whole House"
    ],
    "congress": 11,
    "dates": [
      "1810-12-21"
    ],
    "description": "Read the first and second time, and committed to a committee of the whole House on Monday next. A Bill Providing for the removal of the land office established at Nashville in the state of Tennessee, and Canton in the state of Ohio; and to authorise the register and receiver of public monies to superintend the public sales of land in the district east of Pearl river.",
    "pages": [
      {
        "image": "00440000.tif",
        "page": 1
      },
      {
        "image": "00450002.tif",
        "page": 2
      }
    ],
    "session": 3,
    "volume": 44
  },
  {
    "bill_numbers": [
      "H.R. 13"
    ],
    "chamber": "h",
    "collection": "llhb",
    "committees": [
      "Committee of the Whole House"
    ],
    "congress": 11,
    "dates": [
      "1810-12-26"
    ],
    "description": "Read the first and second time, and committed to a committee of the whole House on Friday next. A Bill Providing for the removal of the land office established at Nashville in the state of Tennessee, and Canton in the state of Ohio; and to authorise the register and receiver of public monies to superintend the public sales of land, in the district east of Pearl river.",
    "pages": [
      {
        "image": "00460000.tif",
        "page": 1
      },
      {
        "image": "00470002.tif",
        "page": 2
      }
    ],
    "session": 3,
    "volume": 44
  },
  {
    "bill_numbers": [
      "H.R. 14"
    ],
    "chamber": "h",
    "collection": "llhb",
    "committees": [
      "Committee of the Whole House"
    ],
    "congress": 11,
    "dates": [
      "1810-12-24"
    ],
    "description": "Read the first and second time, and committed to a committee of the whole House, on Thursday next. A Bill Giving a further compensation to the witnesses who attended the trial of Aaron Burr, before the circuit court of the United States, for the District of Virginia.",
    "pages": [
      {
        "image": "00480000.tif",
        "page": 1
      }
    ],
    "session": 3,
    "volume": 44
  },
  {
    "bill_numbers": [
      "H.R. 15"
    ],
    "chamber": "h",
    "collection": "llhb",
    "committees": [
      "Committee of the Whole House"
    ],
    "congress": 11,
    "dates": [
      "1810-12-27"
    ],
    "description": "Read the first and second time, and committed to a committee of the whole House on Monday next. A Bill To enable the people of the territory of Orleans to form a constitution and state government, and for the admission of such state into the Union, on an equal footing with the original states; and for other purposes.",
    "pages": [
      {
        "image": "00490000.tif",
        "page": 1
      },
      {
        "image": "00500002.tif",
        "page": 2
      },
      {
        "image": "00510003.tif",
        "page": 3
      },
      {
        "image": "00520004.tif",
        "page": 4
      },
      {
        "image": "00530005.tif",
        "page": 5
      }
    ],
    "session": 3,
    "volume": 44
  },
  {
    "bill_numbers": [
      "H.R. 16"
    ],
    "chamber": "h",
    "collection": "llhb",
    "committees": [
      "Committee of the Whole House"
    ],
    "congress": 11,
    "dates": [
      "1810-12-28"
    ],
    "description": "Read the first and second time, and committed to a committee of the whole House, on Tuesday next. A Bill Authorising the Secretary of State to cause a general Index to the laws of the United States to be made, printed and distributed.",
    "pages": [
      {
        "image": "00540000.tif",
        "page": 1
      }
    ],
    "session": 3,
    "volume": 44
  },
  {
    "bill_numbers": [
      "H.R. 17"
    ],
    "chamber": "h",
    "collection": "llhb",
    "committees": [
      "Committee of the Whole House"
    ],
    "congress": 11,
    "dates": [
      "1810-12-28"
    ],
    "description": "Read the first and second time, and committed to a committee of the whole House on Monday next. A Bill In relation to the Pensions and Rations of the Officers of the Navy.",
    "pages": [
      {
        "image": "00550000.tif",
        "page": 1
      },
      {
        "image": "00560002.tif",
        "page": 2
      }
    ],
    "session": 3,
    "volume": 44
  },
  {
    "bill_numbers": [
      "H.R. 18"
    ],
    "chamber": "h",
    "collection": "llhb",
    "committees": [
      "Committee of the Whole House"
    ],
    "congress": 11,
    "dates": [
      "1810-12-29"
    ],
    "description": "Read the first and second time, and committed to a committee of the whole House on Monday next. A Bill Concerning the Bank of Alexandria.",
    "pages": [
      {
        "image": "00570000.tif",
        "page": 1
      },
      {
        "image": "00580002.tif",
        "page": 2
      },
      {
        "image": "00590003.tif",
        "page": 3
      },
      {
        "image": "00600004.tif",
        "page": 4
      },
      {
        "image": "00610005.tif",
        "page": 5
      },
      {
        "image": "00620006.tif",
        "page": 6
      },
      {
        "image": "00630007.tif",
        "page": 7
      },
      {
        "image": "00640008.tif",
        "page": 8
      },
      {
        "image": "00650009.tif",
        "page": 9
      }
    ],
    "session": 3,
    "volume": 44
  },
  {
    "bill_numbers": [
      "H.R. 20"
    ],
    "chamber": "h",
    "collection": "llhb",
    "committees": [
      "Committee of the Whole House"
    ],
    "congress": 11,
    "dates": [
      "1810-12-31"
    ],
    "description": "Read the first and second time, and committed to a committee of the whole House, on Wednesday next. A Bill To revive ''An act to prescribe the mode of taking evidence in cases of contested elections for members of the House of Representatives of the United States, and to compel the attendance of witnesses;'' and in addition to the same.",
    "pages": [
      {
        "image": "00660000.tif",
        "page": 1
      },
      {
        "image": "00670002.tif",
        "page": 2
      }
    ],
    "session": 3,
    "volume": 44
  },
  {
    "bill_numbers": [
      "H.R. 21"
    ],
    "chamber": "h",
    "collection": "llhb",
    "committees": [
      "Committee of the Whole House"
    ],
    "congress": 11,
    "dates": [
      "1810-12-31"
    ],
    "description": "Read the first and second time, and committed to a committee of the whole House on Wednesday next. A Bill To authorise the laying out a Public Road from the line established by the Treaty of Greenville, to the North Bend in the State of Ohio.",
    "pages": [
      {
        "image": "00680000.tif",
        "page": 1
      }
    ],
    "session": 3,
    "volume": 44
  },
  {
    "bill_numbers": [
      "H.R. 22"
    ],
    "chamber": "h",
    "collection": "llhb",
    "committees": [
      "Committee of the Whole House"
    ],
    "congress": 11,
    "dates": [
      "1811-01-03"
    ],
    "description": "Read the first and second time, and committed to a committee of the whole House, on Monday next. A Bill Further providing for the government of the territory of Louisiana.",
    "pages": [
      {
        "image": "00690000.tif",
        "page": 1
      },
      {
        "image": "00700002.tif",
        "page": 2
      },
      {
        "image": "00710003.tif",
        "page": 3
      },
      {
        "image": "00720004.tif",
        "page": 4
      },
      {
        "image": "00730005.tif",
        "page": 5
      },
      {
        "image": "00740006.tif",
        "page": 6
      },
      {
        "image": "00750007.tif",
        "page": 7
      },
      {
        "image": "00760008.tif",
        "page": 8
      },
      {
        "image": "00770009.tif",
        "page": 9
      },
      {
        "image": "00780010.tif",
        "page": 10
      },
      {
        "image": "00790011.tif",
        "page": 11
      },
      {
        "image": "00800012.tif",
        "page": 12
      }
    ],
    "session": 3,
    "volume": 44
  },
  {
    "bill_numbers": [
      "H.R. 23"
    ],
    "chamber": "h",
    "collection": "llhb",
    "committees": [
      "Committee of the Whole House"
    ],
    "congress": 11,
    "dates": [
      "1811-01-03"
    ],
    "description": "Read the first and second time, and committed to a committee of the whole House, on Monday next. A Bill Supplementary to an act, passed the twelfth day of February, one thousand seven hundred and ninety-three, entitled ''An act respecting fugitives from justice, and persons escaping from the service of their masters;'' and for other purposes.",
    "pages": [
      {
        "image": "00810000.tif",
        "page": 1
      },
      {
        "image": "00820002.tif",
        "page": 2
      },
      {
        "image": "00830003.tif",
        "page": 3
      }
    ],
    "session": 3,
    "volume": 44
  },
  {
    "bill_numbers": [
      "H.R. 24"
    ],
    "chamber": "h",
    "collection": "llhb",
    "committees": [
      "Committee of the Whole House"
    ],
    "congress": 11,
    "dates": [
      "1811-01-04"
    ],
    "description": "Read the first and second time, and committed to a committee of the whole House, on Wednesday next. A Bill Establishing Navy Hospitals.",
    "pages": [
      {
        "image": "00840000.tif",
        "page": 1
      },
      {
        "image": "00850002.tif",
        "page": 2
      }
    ],
    "session": 3,
    "volume": 44
  },
  {
    "bill_numbers": [
      "H.R. 25"
    ],
    "chamber": "h",
    "collection": "llhb",
    "committees": [
      "Committee of the Whole House"
    ],
    "congress": 11,
    "dates": [
      "1811-01-04"
    ],
    "description": "Read the first and second time, and committed to a committee of the whole House on Monday next. A Bill Continuing in force for the term of the act, entitled ''An act to incorporate the subscribers to the Bank of the United States,'' on the terms and conditions therein mentioned.",
    "pages": [
      {
        "image": "00860000.tif",
        "page": 1
      },
      {
        "image": "00870002.tif",
        "page": 2
      },
      {
        "image": "00880003.tif",
        "page": 3
      },
      {
        "image": "00890004.tif",
        "page": 4
      },
      {
        "image": "00900005.tif",
        "page": 5
      }
    ],
    "session": 3,
    "volume": 44
  },
  {
    "bill_numbers": [
      "H.R. 26"
    ],
    "chamber": "h",
    "collection": "llhb",
    "committees": [
      "Committee of the Whole House"
    ],
    "congress": 11,
    "dates": [
      "1811-01-07"
    ],
    "description": "Read the first and second time, and committed to a committee of the whole House, on Wednesday next. A Bill To incorporate the subscribers to the Farmers' Bank of Alexandria.",
    "pages": [
      {
        "image": "00910000.tif",
        "page": 1
      },
      {
        "image": "00920002.tif",
        "page": 2
      },
      {
        "image": "00930003.tif",
        "page": 3
      },
      {
        "image": "00940004.tif",
        "page": 4
      },
      {
        "image": "00950005.tif",
        "page": 5
      },
      {
        "image": "00960006.tif",
        "page": 6
      },
      {
        "image": "00970007.tif",
        "page": 7
      },
      {
        "image": "00980008.tif",
        "page": 8
      },
      {
        "image": "00990009.tif",
        "page": 9
      },
      {
        "image": "01000010.tif",
        "page": 10
      },
      {
        "image": "01010011.tif",
        "page": 11
      },
      {
        "image": "01020012.tif",
        "page": 12
      }
    ],
    "session": 3,
    "volume": 44
  },
  {
    "bill_numbers": [
      "H.R. 27"
    ],
    "chamber": "h",
    "collection": "llhb",
    "committees": [
      "Committee of the Whole House"
    ],
    "congress": 11,
    "dates": [
      "1811-01-07"
    ],
    "description": "Read the first and second time, and committed to a committee of the whole House, on Monday next. A Bill For the relief of Richard Tervin, William Coleman, Edwin Lewis, Samuel Mims, Joseph Wilson, and the Baptist Church, at Salem Meeting House, in the Mississippi Territory.",
    "pages": [
      {
        "image": "01030000.tif",
        "page": 1
      },
      {
        "image": "01040002.tif",
        "page": 2
      },
      {
        "image": "01050003.tif",
        "page": 3
      }
    ],
    "session": 3,
    "volume": 44
  },
  {
    "bill_numbers": [
      "H.R. 29"
    ],
    "chamber": "h",
    "collection": "llhb",
    "committees": [
      "Committee of the Whole House"
    ],
    "congress": 11,
    "dates": [
      "1811-01-10"
    ],
    "description": "Read the first and second time, and committed to a committee of the whole House, on Monday next. A Bill To authorise the election of Sheriffs in the Indiana territory.",
    "pages": [
      {
        "image": "01060000.tif",
        "page": 1
      },
      {
        "image": "01070002.tif",
        "page": 2
      }
    ],
    "session": 3,
    "volume": 44
  },
  {
    "bill_numbers": [
      "H.R. 30"
    ],
    "chamber": "h",
    "collection": "llhb",
    "committees": [
      "Committee of the Whole House"
    ],
    "congress": 11,
    "dates": [
      "1811-01-10"
    ],
    "description": "Read the first and second time, and committed to a committee of the whole House, on Monday next. A Bill To amend the Charter of the City of Washington.",
    "pages": [
      {
        "image": "01080000.tif",
        "page": 1
      },
      {
        "image": "01090002.tif",
        "page": 2
      },
      {
        "image": "01100003.tif",
        "page": 3
      },
      {
        "image": "01110004.tif",
        "page": 4
      },
      {
        "image": "01120005.tif",
        "page": 5
      },
      {
        "image": "01130006.tif",
        "page": 6
      },
      {
        "image": "01140007.tif",
        "page": 7
      },
      {
        "image": "01150008.tif",
        "page": 8
      },
      {
        "image": "01160009.tif",
        "page": 9
      }
    ],
    "session": 3,
    "volume": 44
  },
  {
    "bill_numbers": [
      "H.R. 30"
    ],
    "chamber": "h",
    "collection": "llhb",
    "committees": [
      "Committee of the Whole House"
    ],
    "congress": 11,
    "dates": [
      "1811-01-10"
    ],
    "description": "Read the first and second time, and committed to a committee of the whole House, on Monday next. A Bill To amend the Charter of the City of Washington.",
    "pages": [
      {
        "image": "01170000.tif",
        "page": 1
      },
      {
        "image": "01180002.tif",
        "page": 2
      },
      {
        "image": "01190003.tif",
        "page": 3
      },
      {
        "image": "01200004.tif",
        "page": 4
      },
      {
        "image": "01210005.tif",
        "page": 5
      },
      {
        "image": "01220006.tif",
        "page": 6
      },
      {
        "image": "01230007.tif",
        "page": 7
      },
      {
        "image": "01240008.tif",
        "page": 8
      },
      {
        "image": "01250009.tif",
        "page": 9
      }
    ],
    "session": 3,
    "volume": 44
  },
  {
    "bill_numbers": [
      "H.R. 31"
    ],
    "chamber": "h",
    "collection": "llhb",
    "committees": [
      "Committee of the Whole House"
    ],
    "congress": 11,
    "dates": [
      "1811-01-15"
    ],
    "description": "Read the first and second time, and committed to a committee of the whole House, on Monday next. A Bill Supplementary to the act concerning the commercial intercourse between the United States and Great Britain and France, and for other purposes.",
    "pages": [
      {
        "image": "01260000.tif",
        "page": 1
      },
      {
        "image": "01270002.tif",
        "page": 2
      },
      {
        "image": "01280003.tif",
        "page": 3
      },
      {
        "image": "01290004.tif",
        "page": 4
      },
      {
        "image": "01300005.tif",
        "page": 5
      },
      {
        "image": "01310006.tif",
        "page": 6
      },
      {
        "image": "01320007.tif",
        "page": 7
      },
      {
        "image": "01330008.tif",
        "page": 8
      },
      {
        "image": "01340009.tif",
        "page": 9
      },
      {
        "image": "01350010.tif",
        "page": 10
      }
    ],
    "session": 3,
    "volume": 44
  },
  {
    "bill_numbers": [
      "H.R. 31"
    ],
    "chamber": "h",
    "collection": "llhb",
    "committees": [],
    "congress": 11,
    "dates": [
      "1811-01-29"
    ],
    "description": "Ordered To Be Printed. Amendment Proposed by Mr Eppes, to the bill ''Supplemental to the act concerning the commercial intercourse between the United States and Great Britain and France, and for other purposes.''",
    "pages": [
      {
        "image": "01360000.tif",
        "page": 1
      }
    ],
    "session": 3,
    "volume": 44
  },
  {
    "bill_numbers": [
      "H.R. 33"
    ],
    "chamber": "h",
    "collection": "llhb",
    "committees": [
      "Committee of the Whole House"
    ],
    "congress": 11,
    "dates": [
      "1811-01-17"
    ],
    "description": "Read the first and second time, and committed to a committee of the whole House, on Saturday next. A Bill Making appropriations for the support of government for the year one thousand eight hundred and eleven.",
    "pages": [
      {
        "image": "01370000.tif",
        "page": 1
      },
      {
        "image": "01380002.tif",
        "page": 2
      },
      {
        "image": "01390003.tif",
        "page": 3
      },
      {
        "image": "01400004.tif",
        "page": 4
      },
      {
        "image": "01410005.tif",
        "page": 5
      },
      {
        "image": "01420006.tif",
        "page": 6
      },
      {
        "image": "01430007.tif",
        "page": 7
      },
      {
        "image": "01440008.tif",
        "page": 8
      },
      {
        "image": "01450009.tif",
        "page": 9
      },
      {
        "image": "01460010.tif",
        "page": 10
      },
      {
        "image": "01470011.tif",
        "page": 11
      },
      {
        "image": "01480012.tif",
        "page": 12
      },
      {
        "image": "01490013.tif",
        "page": 13
      }
    ],
    "session": 3,
    "volume": 44
  },
  {
    "bill_numbers": [
      "H.R. 34"
    ],
    "chamber": "h",
    "collection": "llhb",
    "committees": [
      "Committee of the Whole House"
    ],
    "congress": 11,
    "dates": [
      "1811-01-17"
    ],
    "description": "Read the first and second time, and committed to a committee of the whole House, on Saturday next. A Bill Making appropriations for the support of the Military establishment of the United States, for the year one thousand eight hundred and eleven.",
    "pages": [
      {
        "image": "01500000.tif",
        "page": 1
      },
      {
        "image": "01510002.tif",
        "page": 2
      }
    ],
    "session": 3,
    "volume": 44
  },
  {
    "bill_numbers": [
      "H.R. 35"
    ],
    "chamber": "h",
    "collection": "llhb",
    "committees": [
      "Committee of the Whole House"
    ],
    "congress": 11,
    "dates": [
      "1811-01-17"
    ],
    "description": "Read the first and second time, and committed to a committee of the whole House, on Saturday next. A Bill Making appropriations for the support of the Navy of the United States, for the year one thousand eight hundred and eleven.",
    "pages": [
      {
        "image": "01520000.tif",
        "page": 1
      },
      {
        "image": "01530002.tif",
        "page": 2
      }
    ],
    "session": 3,
    "volume": 44
  },
  {
    "bill_numbers": [
      "H.R. 36"
    ],
    "chamber": "h",
    "collection": "llhb",
    "committees": [
      "Committee of the Whole House"
    ],
    "congress": 11,
    "dates": [
      "1811-01-17"
    ],
    "description": "Read the first and second time, and committed to a committee of the whole House, on Saturday next. A Bill For establishing trading houses with the Indian tribes.",
    "pages": [
      {
        "image": "01540000.tif",
        "page": 1
      },
      {
        "image": "01550002.tif",
        "page": 2
      },
      {
        "image": "01560003.tif",
        "page": 3
      },
      {
        "image": "01570004.tif",
        "page": 4
      },
      {
        "image": "01580005.tif",
        "page": 5
      },
      {
        "image": "01590006.tif",
        "page": 6
      },
      {
        "image": "01600007.tif",
        "page": 7
      },
      {
        "image": "01610008.tif",
        "page": 8
      },
      {
        "image": "01620009.tif",
        "page": 9
      }
    ],
    "session": 3,
    "volume": 44
  },
  {
    "bill_numbers": [
      "H.R. 37"
    ],
    "chamber": "h",
    "collection": "llhb",
    "committees": [
      "Committee of the Whole House"
    ],
    "congress": 11,
    "dates": [
      "1811-01-17"
    ],
    "description": "Read the first and second time, and committed to a committee of the whole House, on Monday next. A Bill Making an appropriation for building a jail in Alexandria county, in the district of Columbia, and for other purposes.",
    "pages": [
      {
        "image": "01630000.tif",
        "page": 1
      },
      {
        "image": "01640002.tif",
        "page": 2
      }
    ],
    "session": 3,
    "volume": 44
  },
  {
    "bill_numbers": [
      "H.R. 38"
    ],
    "chamber": "h",
    "collection": "llhb",
    "committees": [
      "Committee of the Whole House"
    ],
    "congress": 11,
    "dates": [
      "1811-01-19"
    ],
    "description": "Read the first and second time, and committed to a committee of the whole House, on Monday next. A Bill For the encouragement of learning, and for the promotion of the useful arts.",
    "pages": [
      {
        "image": "01650000.tif",
        "page": 1
      },
      {
        "image": "01660002.tif",
        "page": 2
      },
      {
        "image": "01670003.tif",
        "page": 3
      },
      {
        "image": "01680004.tif",
        "page": 4
      },
      {
        "image": "01690005.tif",
        "page": 5
      },
      {
        "image": "01700006.tif",
        "page": 6
      },
      {
        "image": "01710007.tif",
        "page": 7
      },
      {
        "image": "01720008.tif",
        "page": 8
      },
      {
        "image": "01730009.tif",
        "page": 9
      },
      {
        "image": "01740010.tif",
        "page": 10
      },
      {
        "image": "01750011.tif",
        "page": 11
      },
      {
        "image": "01760012.tif",
        "page": 12
      },
      {
        "image": "01770013.tif",
        "page": 13
      },
      {
        "image": "01780014.tif",
        "page": 14
      },
      {
        "image": "01790015.tif",
        "page": 15
      },
      {
        "image": "01800016.tif",
        "page": 16
      },
      {
        "image": "01810017.tif",
        "page": 17
      },
      {
        "image": "01820018.tif",
        "page": 18
      }
    ],
    "session": 3,
    "volume": 44
  },
  {
    "bill_numbers": [
      "H.R. 39"
    ],
    "chamber": "h",
    "collection": "llhb",
    "committees": [
      "Committee of the Whole House"
    ],
    "congress": 11,
    "dates": [
      "1811-01-19"
    ],
    "description": "Read the first and second time, and committed to a committee of the whole House, on Monday next. A Bill To remit certain fines, penalties and forfeitures.",
    "pages": [
      {
        "image": "01830000.tif",
        "page": 1
      },
      {
        "image": "01840002.tif",
        "page": 2
      }
    ],
    "session": 3,
    "volume": 44
  },
  {
    "bill_numbers": [
      "H.R. 40"
    ],
    "chamber": "h",
    "collection": "llhb",
    "committees": [
      "Committee of the Whole House"
    ],
    "congress": 11,
    "dates": [
      "1811-01-23"
    ],
    "description": "Read the first and second time, and committed to a committee of the whole House to-morrow. A Bill To amend an act, entitled, ''An act to regulate and fix the compensation of clerks, and to authorise the laying out of certain public roads, and for other purposes.''",
    "pages": [
      {
        "image": "01850000.tif",
        "page": 1
      },
      {
        "image": "01860002.tif",
        "page": 2
      },
      {
        "image": "01870003.tif",
        "page": 3
      },
      {
        "image": "01880004.tif",
        "page": 4
      },
      {
        "image": "01890005.tif",
        "page": 5
      },
      {
        "image": "01900006.tif",
        "page": 6
      },
      {
        "image": "01910007.tif",
        "page": 7
      },
      {
        "image": "01920008.tif",
        "page": 8
      }
    ],
    "session": 3,
    "volume": 44
  },
  {
    "bill_numbers": [
      "H.R. 42"
    ],
    "chamber": "h",
    "collection": "llhb",
    "committees": [
      "Committee of the Whole House"
    ],
    "congress": 11,
    "dates": [
      "1811-01-24"
    ],
    "description": "Read the first and second time, and committed to a committee of the whole House on Monday next. A Bill Providing for the sale of a tract of land lying in the state of Tennessee, and a tract in the Indiana territory.",
    "pages": [
      {
        "image": "01930000.tif",
        "page": 1
      },
      {
        "image": "01940002.tif",
        "page": 2
      },
      {
        "image": "01950003.tif",
        "page": 3
      }
    ],
    "session": 3,
    "volume": 44
  },
  {
    "bill_numbers": [
      "H.R. 43"
    ],
    "chamber": "h",
    "collection": "llhb",
    "committees": [
      "Committee of the Whole House"
    ],
    "congress": 11,
    "dates": [
      "1811-01-29"
    ],
    "description": "Read the first and second time, and committed to a committee of the whole House, on Saturday next. B Bill Providing for the more convenient taking of affidavits and bail in civil causes, depending in the courts of the United States.",
    "pages": [
      {
        "image": "01960000.tif",
        "page": 1
      },
      {
        "image": "01970002.tif",
        "page": 2
      }
    ],
    "session": 3,
    "volume": 44
  },
  {
    "bill_numbers": [
      "H.R. 44"
    ],
    "chamber": "h",
    "collection": "llhb",
    "committees": [
      "Committee of the Whole House"
    ],
    "congress": 11,
    "dates": [
      "1811-01-30"
    ],
    "description": "Read the first and second time, and committed to a committee of the whole House on Saturday next. A Bill Making an additional appropriation for the Navy.",
    "pages": [
      {
        "image": "01980000.tif",
        "page": 1
      }
    ],
    "session": 3,
    "volume": 44
  },
  {
    "bill_numbers": [
      "H.R. 45"
    ],
    "chamber": "h",
    "collection": "llhb",
    "committees": [
      "Committee of the Whole House"
    ],
    "congress": 11,
    "dates": [
      "1811-01-30"
    ],
    "description": "Read the first and second time, and committed to a committee of the whole House, on Wednesday next. A Bill To provide for warming and ventilating the hall of the House of Representatives by a Rarifying Air Stove.",
    "pages": [
      {
        "image": "01990000.tif",
        "page": 1
      }
    ],
    "session": 3,
    "volume": 44
  },
  {
    "bill_numbers": [
      "H.R. 46"
    ],
    "chamber": "h",
    "collection": "llhb",
    "committees": [
      "Committee of the Whole House"
    ],
    "congress": 11,
    "dates": [
      "1811-01-30"
    ],
    "description": "Read the first and second time, and committed to a committee of the whole House, on Tuesday next. A Bill Authorising the sale and grant of a certain quantity of public land to the proprietors of the Middlesex Canal.",
    "pages": [
      {
        "image": "02000000.tif",
        "page": 1
      },
      {
        "image": "02010002.tif",
        "page": 2
      },
      {
        "image": "02020003.tif",
        "page": 3
      },
      {
        "image": "02030004.tif",
        "page": 4
      },
      {
        "image": "02040005.tif",
        "page": 5
      }
    ],
    "session": 3,
    "volume": 44
  },
  {
    "bill_numbers": [
      "H.R. 47"
    ],
    "chamber": "h",
    "collection": "llhb",
    "committees": [
      "Committee of the Whole House"
    ],
    "congress": 11,
    "dates": [
      "1811-01-31"
    ],
    "description": "Read the first and second time, and committed to a committee of the whole House, to-morrow. A Bill To increase the salaries of the Judges of the Circuit Court for the District of Columbia.",
    "pages": [
      {
        "image": "02050000.tif",
        "page": 1
      }
    ],
    "session": 3,
    "volume": 44
  },
  {
    "bill_numbers": [
      "H.R. 48"
    ],
    "chamber": "h",
    "collection": "llhb",
    "committees": [
      "Committee of the Whole House"
    ],
    "congress": 11,
    "dates": [
      "1811-01-31"
    ],
    "description": "Read the first and second time, and committed to a committee of the whole House, on Tuesday next. A Bill To secure to vessels of the United States an equal advantage in exporting articles the growth or produce of the United States to foreign ports, and for other purposes.",
    "pages": [
      {
        "image": "02060000.tif",
        "page": 1
      },
      {
        "image": "02070002.tif",
        "page": 2
      },
      {
        "image": "02080003.tif",
        "page": 3
      },
      {
        "image": "02090004.tif",
        "page": 4
      }
    ],
    "session": 3,
    "volume": 44
  },
  {
    "bill_numbers": [
      "H.R. 49"
    ],
    "chamber": "h",
    "collection": "llhb",
    "committees": [
      "Committee of the Whole House"
    ],
    "congress": 11,
    "dates": [
      "1811-01-31"
    ],
    "description": "Read the first and second time, and committed to a committee of the whole House on Wednesday next. A Bill For the relief of Jared Shattuck.",
    "pages": [
      {
        "image": "02100000.tif",
        "page": 1
      },
      {
        "image": "02110002.tif",
        "page": 2
      }
    ],
    "session": 3,
    "volume": 44
  },
  {
    "bill_numbers": [
      "H.R. 50"
    ],
    "chamber": "h",
    "collection": "llhb",
    "committees": [
      "Committee of the Whole House"
    ],
    "congress": 11,
    "dates": [
      "1811-02-04"
    ],
    "description": "Read the first and second time, and committed to a committee of the whole House, on Thursday next. A Bill To enable the people of the Mississippi Territory, to form a constitution and state government, and for the admission of such State into the Union, on an equal footing with the original States.",
    "pages": [
      {
        "image": "02120000.tif",
        "page": 1
      },
      {
        "image": "02130002.tif",
        "page": 2
      },
      {
        "image": "02140003.tif",
        "page": 3
      },
      {
        "image": "02150004.tif",
        "page": 4
      }
    ],
    "session": 3,
    "volume": 44
  },
  {
    "bill_numbers": [
      "H.R. 51"
    ],
    "chamber": "h",
    "collection": "llhb",
    "committees": [
      "Committee of the Whole House"
    ],
    "congress": 11,
    "dates": [
      "1811-02-04"
    ],
    "description": "Read the first and second time, and committed to a committee of the whole House, to-morrow. A Bill For the disposal of certain copies of a collection of the laws, treaties and other documents relative to the Public Lands.",
    "pages": [
      {
        "image": "02160000.tif",
        "page": 1
      },
      {
        "image": "02170002.tif",
        "page": 2
      }
    ],
    "session": 3,
    "volume": 44
  },
  {
    "bill_numbers": [
      "H.R. 52"
    ],
    "chamber": "h",
    "collection": "llhb",
    "committees": [
      "Committee of the Whole House"
    ],
    "congress": 11,
    "dates": [
      "1811-02-04"
    ],
    "description": "Read the first and second time, and committed to a committee of the whole House to-morrow. A Bill Supplementary to the act, entitled ''An act concerning the commercial intercourse between the United States and Great Britain and France and their dependencies, and for other purposes.''",
    "pages": [
      {
        "image": "02180000.tif",
        "page": 1
      }
    ],
    "session": 3,
    "volume": 44
  },
  {
    "bill_numbers": [
      "H.R. 53"
    ],
    "chamber": "h",
    "collection": "llhb",
    "committees": [
      "Committee of the Whole House"
    ],
    "congress": 11,
    "dates": [
      "1811-02-06"
    ],
    "description": "Read the first and second time, and committed to a committee of the whole House, on Tuesday next. A Bill Authorising a loan of money, for a sum not exceeding",
    "pages": [
      {
        "image": "02190000.tif",
        "page": 1
      },
      {
        "image": "02200002.tif",
        "page": 2
      },
      {
        "image": "02210003.tif",
        "page": 3
      }
    ],
    "session": 3,
    "volume": 44
  },
  {
    "bill_numbers": [
      "H.R. 55"
    ],
    "chamber": "h",
    "collection": "llhb",
    "committees": [
      "Committee of the Whole House"
    ],
    "congress": 11,
    "dates": [
      "1811-02-06"
    ],
    "description": "Read the first and second time, and committed to a committee of the whole House on Monday next. A Bill For imposing additional duties, upon all goods, wares and merchandise, imported from any foreign port or place.",
    "pages": [
      {
        "image": "02220000.tif",
        "page": 1
      },
      {
        "image": "02230002.tif",
        "page": 2
      }
    ],
    "session": 3,
    "volume": 44
  },
  {
    "bill_numbers": [
      "H.R. 55"
    ],
    "chamber": "h",
    "collection": "llhb",
    "committees": [
      "Committee of the Whole House"
    ],
    "congress": 11,
    "dates": [
      "1811-02-06"
    ],
    "description": "Read the first and second time, and committed to a committee of the whole House, on Monday next. A Bill Making further appropriations for completing the Capitol, and for other purposes.",
    "pages": [
      {
        "image": "02240000.tif",
        "page": 1
      },
      {
        "image": "02250002.tif",
        "page": 2
      },
      {
        "image": "02260003.tif",
        "page": 3
      }
    ],
    "session": 3,
    "volume": 44
  },
  {
    "bill_numbers": [
      "H.R. 56"
    ],
    "chamber": "h",
    "collection": "llhb",
    "committees": [
      "Committee of the Whole House"
    ],
    "congress": 11,
    "dates": [
      "1811-02-07"
    ],
    "description": "Twice read, and committed to a committee of the whole House on Monday next. A Bill To amend an act, entitled ''An act regulating the Post Office establishment.''",
    "pages": [
      {
        "image": "02270000.tif",
        "page": 1
      },
      {
        "image": "02280002.tif",
        "page": 2
      }
    ],
    "session": 3,
    "volume": 44
  },
  {
    "bill_numbers": [
      "H.R. 59"
    ],
    "chamber": "h",
    "collection": "llhb",
    "committees": [
      "Committee of the Whole House"
    ],
    "congress": 11,
    "dates": [
      "1811-02-09"
    ],
    "description": "Read the first and second time, and committed to a committee of the whole House on Monday next. A Bill For the relief of Thomas and John Clifford of Philadelphia, and Charles Wirgman of Baltimore.",
    "pages": [
      {
        "image": "02290000.tif",
        "page": 1
      }
    ],
    "session": 3,
    "volume": 44
  },
  {
    "bill_numbers": [
      "H.R. 60"
    ],
    "chamber": "h",
    "collection": "llhb",
    "committees": [
      "Committee of the Whole House"
    ],
    "congress": 11,
    "dates": [
      "1811-02-11"
    ],
    "description": "Read the first and second time, and committed to a committee of the whole House, on Friday next. A Bill For the relief of Arthur St. Clair.",
    "pages": [
      {
        "image": "02300000.tif",
        "page": 1
      }
    ],
    "session": 3,
    "volume": 44
  },
  {
    "bill_numbers": [
      "H.R. 61"
    ],
    "chamber": "h",
    "collection": "llhb",
    "committees": [
      "Committee of the Whole House"
    ],
    "congress": 11,
    "dates": [
      "1811-02-14"
    ],
    "description": "Read the first and second time, and committed to a committee of the whole House, on Saturday next. A Bill Providing for the more effectual accountability of persons entrusted with the expenditure of public monies.",
    "pages": [
      {
        "image": "02310000.tif",
        "page": 1
      },
      {
        "image": "02320002.tif",
        "page": 2
      },
      {
        "image": "02330003.tif",
        "page": 3
      }
    ],
    "session": 3,
    "volume": 44
  },
  {
    "bill_numbers": [
      "H.R. 62"
    ],
    "chamber": "h",
    "collection": "llhb",
    "committees": [
      "Committee of the Whole House"
    ],
    "congress": 11,
    "dates": [
      "1811-02-13",
      "1811-02-14"
    ],
    "description": "Received. Read the first and second time, and committed to a committee of the whole House, on Saturday next. A Bill More effectually to provide for Arming and Disciplining the Militia of the United States.",
    "pages": [
      {
        "image": "02340000.tif",
        "page": 1
      },
      {
        "image": "02350002.tif",
        "page": 2
      },
      {
        "image": "02360003.tif",
        "page": 3
      },
      {
        "image": "02370004.tif",
        "page": 4
      },
      {
        "image": "02380005.tif",
        "page": 5
      },
      {
        "image": "02390006.tif",
        "page": 6
      }
    ],
    "session": 3,
    "volume": 44
  },
  {
    "bill_numbers": [
      "H.R. 63"
    ],
    "chamber": "h",
    "collection": "llhb",
    "committees": [
      "Committee of the Whole House"
    ],
    "congress": 11,
    "dates": [
      "1811-02-14"
    ],
    "description": "Read the first and second time, and committed to a committee of the whole House, on Monday next. A Bill For the establishment, government and protection of the Mobile Territory.",
    "pages": [
      {
        "image": "02400000.tif",
        "page": 1
      },
      {
        "image": "02410002.tif",
        "page": 2
      },
      {
        "image": "02420003.tif",
        "page": 3
      },
      {
        "image": "02430004.tif",
        "page": 4
      },
      {
        "image": "02440005.tif",
        "page": 5
      },
      {
        "image": "02450006.tif",
        "page": 6
      }
    ],
    "session": 3,
    "volume": 44
  },
  {
    "bill_numbers": [
      "H.R. 64"
    ],
    "chamber": "h",
    "collection": "llhb",
    "committees": [
      "Committee of the Whole House"
    ],
    "congress": 11,
    "dates": [
      "1811-02-14"
    ],
    "description": "Read the first and second time, and committed to a committee of the whole House to-morrow. A Bill Making a further appropriation for the support of a Library.",
    "pages": [
      {
        "image": "02460000.tif",
        "page": 1
      }
    ],
    "session": 3,
    "volume": 44
  },
  {
    "bill_numbers": [
      "H.R. 65"
    ],
    "chamber": "h",
    "collection": "llhb",
    "committees": [
      "Committee of the Whole House"
    ],
    "congress": 11,
    "dates": [
      "1811-02-15"
    ],
    "description": "Read the first and second time, and referred to a committee of the whole House, to-morrow. A Bill To annex a part of the state of New Jersey to the collection district of New York; to remove the office of collector of Niagara to Lewiston; to establish a new district to be called the District of St. Lawrence; to make Cape St. Vincent, in the district of Sacket's harbor, a port of delivery; and out of the districts of Miami and Mississippi to make tow new districts, to be called the Districts of Sandusky and Teche; and for other purposes.",
    "pages": [
      {
        "image": "02470000.tif",
        "page": 1
      },
      {
        "image": "02480002.tif",
        "page": 2
      },
      {
        "image": "02490003.tif",
        "page": 3
      },
      {
        "image": "02500004.tif",
        "page": 4
      }
    ],
    "session": 3,
    "volume": 44
  },
  {
    "bill_numbers": [
      "H.R. 67"
    ],
    "chamber": "h",
    "collection": "llhb",
    "committees": [
      "Committee of the Whole House"
    ],
    "congress": 11,
    "dates": [
      "1811-02-20"
    ],
    "description": "Read the first and second time, and committed to a committee of the whole House, on Monday next. A Bill Authorising the President of the United States, to accept the service of a number of Volunteer Companies, not exceeding fifty thousand men.",
    "pages": [
      {
        "image": "02510000.tif",
        "page": 1
      },
      {
        "image": "02520002.tif",
        "page": 2
      },
      {
        "image": "02530003.tif",
        "page": 3
      },
      {
        "image": "02540004.tif",
        "page": 4
      }
    ],
    "session": 3,
    "volume": 44
  },
  {
    "bill_numbers": [
      "H.R. 68"
    ],
    "chamber": "h",
    "collection": "llhb",
    "committees": [
      "Committee of the Whole House"
    ],
    "congress": 11,
    "dates": [
      "1811-02-21"
    ],
    "description": "Read the first and second time, and committed to a committee of the whole House on Saturday next. A Bill Making appropriations for carrying into effect a treaty between the United States and the Great and Little Osage nations of Indians, concluded at Fort Clarke, on the tent day of November, one thousand eight hundred and eight.",
    "pages": [
      {
        "image": "02550000.tif",
        "page": 1
      }
    ],
    "session": 3,
    "volume": 44
  },
  {
    "bill_numbers": [
      "H.R. 69"
    ],
    "chamber": "h",
    "collection": "llhb",
    "committees": [
      "Committee of the Whole House"
    ],
    "congress": 11,
    "dates": [
      "1811-02-21"
    ],
    "description": "Read the first and second time, and committed to a committee of the whole House on Saturday next. A Bill Repealing the tenth section of the act, to incorporate the subscribers to the Bank of the United States.",
    "pages": [
      {
        "image": "02560000.tif",
        "page": 1
      }
    ],
    "session": 3,
    "volume": 44
  },
  {
    "bill_numbers": [
      "H.R. 70"
    ],
    "chamber": "h",
    "collection": "llhb",
    "committees": [
      "Committee of the Whole House"
    ],
    "congress": 11,
    "dates": [
      "1811-02-21"
    ],
    "description": "Read the first and second time, and committed to a committee of the whole House on Saturday next. A Bill For allowing additional compensation to the Post-Master General.",
    "pages": [
      {
        "image": "02570000.tif",
        "page": 1
      }
    ],
    "session": 3,
    "volume": 44
  },
  {
    "bill_numbers": [
      "H.R. 72"
    ],
    "chamber": "h",
    "collection": "llhb",
    "committees": [
      "Committee of the Whole House"
    ],
    "congress": 11,
    "dates": [
      "1811-03-01"
    ],
    "description": "Read the first and second time, and committed to a committee of the whole House to-morrow. A Bill Concerning Invalid Pensioners.",
    "pages": [
      {
        "image": "02580000.tif",
        "page": 1
      },
      {
        "image": "02590002.tif",
        "page": 2
      },
      {
        "image": "02600003.tif",
        "page": 3
      },
      {
        "image": "02610004.tif",
        "page": 4
      },
      {
        "image": "02620005.tif",
        "page": 5
      },
      {
        "image": "02630006.tif",
        "page": 6
      }
    ],
    "session": 3,
    "volume": 44
  },
  {
    "bill_numbers": [
      "H.R. 73"
    ],
    "chamber": "h",
    "collection": "llhb",
    "committees": [],
    "congress": 11,
    "dates": [
      "1811-02-23"
    ],
    "description": "Read the first and second time, and referred to the select committee on the same subject. An Act To extend the right of suffrage in the Indiana territory, and for other purposes.",
    "pages": [
      {
        "image": "02640000.tif",
        "page": 1
      },
      {
        "image": "02650002.tif",
        "page": 2
      }
    ],
    "session": 3,
    "volume": 44
  },
  {
    "bill_numbers": [
      "H.R. 74"
    ],
    "chamber": "h",
    "collection": "llhb",
    "committees": [
      "Committee of the Whole House"
    ],
    "congress": 11,
    "dates": [
      "1811-01-15"
    ],
    "description": "Read the first and second time, and committed to a committee of the whole House, on Friday next. An Art Authorising the sale and grant of a certain quantity of public land to the Chesapeake and Delaware Canal Company.",
    "pages": [
      {
        "image": "02660000.tif",
        "page": 1
      },
      {
        "image": "02670002.tif",
        "page": 2
      },
      {
        "image": "02680003.tif",
        "page": 3
      },
      {
        "image": "02690004.tif",
        "page": 4
      },
      {
        "image": "02700005.tif",
        "page": 5
      }
    ],
    "session": 3,
    "volume": 44
  },
  {
    "bill_numbers": [
      "H.R. 75"
    ],
    "chamber": "h",
    "collection": "llhb",
    "committees": [],
    "congress": 11,
    "dates": [
      "1811-02-12"
    ],
    "description": "Read the first and second time, and referred to the committee appointed on that part of the message of the President of the United States, as relates to the corps of engineers and military academy. An Art Making further provision for the corps of Engineers.",
    "pages": [
      {
        "image": "02710000.tif",
        "page": 1
      },
      {
        "image": "02720002.tif",
        "page": 2
      },
      {
        "image": "02730003.tif",
        "page": 3
      },
      {
        "image": "02740004.tif",
        "page": 4
      },
      {
        "image": "02750005.tif",
        "page": 5
      }
    ],
    "session": 3,
    "volume": 44
  },
  {
    "bill_numbers": [
      "H.R. 76"
    ],
    "chamber": "h",
    "collection": "llhb",
    "committees": [
      "Committee of the Whole House"
    ],
    "congress": 11,
    "dates": [
      "1811-02-15"
    ],
    "description": "Read, and referred to a committee of the whole House on Monday next. The committee, to whom was referred the bill from the Senate making further provision for the corps of engineers, report the following Amendments:",
    "pages": [
      {
        "image": "02760000.tif",
        "page": 1
      }
    ],
    "session": 3,
    "volume": 44
  },
  {
    "bill_numbers": [
      "H.R. 77"
    ],
    "chamber": "h",
    "collection": "llhb",
    "committees": [
      "Committee of the Whole House"
    ],
    "congress": 11,
    "dates": [
      "1811-02-02",
      "1811-02-04"
    ],
    "description": "Reported. Read the first and second time, and committed, together with the bill, to a committee of the whole House, to-morrow. Amendments Reported by the select committee, on the several bills from the Senate, to charter sundry Banks in the district of Columbia, to the bill to incorporate the Potomac Bank.",
    "pages": [
      {
        "image": "02770000.tif",
        "page": 1
      },
      {
        "image": "02780002.tif",
        "page": 2
      }
    ],
    "session": 3,
    "volume": 44
  }
]